Workbook

Sheet Beschreibung
C3: 150 analysierbare Beiträge mit Kaffee wurden aus dem Korpus extrahiert. Nicht analysierbare Beiträge, wie etwa Hyperlinks mit Kaffee, wurden von der Untersuchung ausgeschlossen, wie das Beispiel unten:
C7: WDD17/A11.44456 Diskussion:Arabica-Kaffee, In: Wikipedia - URL:http://de.wikipedia.org/wiki/Diskussion:Arabica-Kaffee: Wikipedia, 2017
C9: Insgesamt wurden 2276 Beiträge mit Kaffee im Korpus von dem Algorithmus analysiert. Die Genuszuweisungen von Kaffee wurden davon wie folgt zugeordnet:
D13: Ergebnis | G13: n | H13: %
D14: Nicht feststellbar | G14: 1228 | H14: =G14/G$17 -> 0.53954306
D15: Maskulinium oder Neutrum | G15: 973 | H15: =G15/G$17 -> 0.42750439
D16: Femininum | G16: 75 | H16: =G16/G$17 -> 0.032952548
D17: Summe | G17: =SUM(G14:G16) -> 2276 | H17: =SUM(H14:H16) -> 1
B22: Siehe „Manuelle Überprüfung von 150" für die durchgeführte Überprüfung, der in der Arbeit beschrieben wird.
B24: Gunnar Brådvik
B25: gunnar@bradvik.se
B26: 3. Februar 2026

Sheet Manuelle Überprüfung von 150
A1: Nummer | B1: Beitrag | C1: Genuszuweisung (manuell) | D1: Genuszuweisung (Algorithmus) | E1: Korrektes Ergebnis vom Algorithmus | F1: Kommentar/Grund des Fehlers
A2: 1 | B2: Hitler war seit seiner Jugendzeit Nichtraucher und trank keinen Alkohol, später auch keinen Kaffee und Schwarztee. Zudem wurde er 1932 aus Furcht vor einer Magenkrebserkrankung gemäßigter Vegetarier. Diese Ernährungsgewohnheiten behielt er als Reichskanzler bei und thematisierte sie in Monologen vor dem engsten Anhängerkreis auch als Mittel für die nationalsozialistische Gesundheitspolitik." " | C2: Maskulinum oder Neutrum | D2: Maskulinum oder Neutrum | E2: =IF(C2="NICHT-ANALYSIERT", "NA", IF(C2=D2, 1, 0)) -> 1 | F2: Negationsartikel (-en), Akkusativ
A3: 2 | B3: Ich glaube bzg. Koffeinsucht sollte man sich mal in Gefängnissen umhören. Da wird z.B. löslicher Kaffee mit Cola aufgemischt um sich anzudröhnen. Dies hat alle Merkmale einer Sucht! Evtl. braucht man ein anderes Wort dafür. Aber auch die Entzugerscheinungen eines ausgibigen, regelmäßigen Kaffee-Trinkers entsprechen den Suchtdefinitionen. | C3: Maskulinum oder Neutrum | D3: Maskulinum oder Neutrum | E3: =IF(C3="NICHT-ANALYSIERT", "NA", IF(C3=D3, 1, 0)) -> 1 | F3: Adjektivflexion, -er
A4: 3 | B4: Da die Volkswirtschaft sehr von den Erlösen aus landwirtschaftlichem Anbau abhängt (Kaffee, Kakao, Palmöl, Holz etc.) sind bei einem weltweitem Überangebot dieser Produkte die Erlöse seit Jahren rückläufig, was sich sicherlich langfristig nicht positv auf die Stabilität, Sicherheit etc. auswirken kann. Verursacher hierfür ist meines Erachten vor Allem der Westen (Europäische Gemeinschaft, Weltbank etc.), die vielen afrikanischen Staaten Kredite aufgedrängt und sie dann in eine Überproduktion der o. g. landwirtschaftlichen Güter geführt haben, was die Abhängigkeit vom Westen dann noch mehr verstärkt hat. So sind die Exportpreise für Kaffee / Kakao seit Jahrzehnten rückläufig... | C4: Nicht feststellbar | D4: Nicht feststellbar | E4: =IF(C4="NICHT-ANALYSIERT", "NA", IF(C4=D4, 1, 0)) -> 1
A5: 4 | B5: 3. Helicobacter ist die Hauptursache f. gastrointestinale Ulcera, aber nicht die einzige Ursache f. Übersäuerung des Magens, wie der Autor des Kommentars Aufstoßen - nein Danke!" behauptet. Eine H.p.-Eradikationstherapie bei ernährungsbedingten Beschwerden (zu viel Alkohol, Kaffee, fetthaltige Speisen) wäre unsinnig rausgeblasenes Geld. Darüber hinaus sind die Protonenpumpenhemmer bei der Eradikationstherapie die einzigen Medikamente, die die Magenschmerzen mindern (Ausnahme: bei der Quadrupeltherpie hat das Bismut einen positiven Effekt auf die Schleimproduktion und endogene Bikarbonatausscheidung). Im Übrigen: wer 3-4h nach Natrongabe aufstoßen muß, hat eindeutig zu viel genommen. 10:02, 15. Aug. 2008 (CEST) " | C5: Nicht feststellbar | D5: Nicht feststellbar | E5: =IF(C5="NICHT-ANALYSIERT", "NA", IF(C5=D5, 1, 0)) -> 1
A6: 5 | B6: Unabhängig davon: Was das CERN produzieren und speichern kann, wäre als Energiespeicher völlig witzlos. Hätte man sämtliche dort (innerhalb von Jahrzehnten) erzeugte Antimaterie gleichzeitig zur Verfügung, könnte man damit etwa einmal Kaffee kochen. -- 11:08, 26. Nov. 2013 (CET) | C6: Nicht feststellbar | D6: Nicht feststellbar | E6: =IF(C6="NICHT-ANALYSIERT", "NA", IF(C6=D6, 1, 0)) -> 1
A7: 6 | B7: Woher die Tasse kommt? Wolltest nicht Du in Deiner ersten Antwort etwa einmal Kaffee kochen."? Gruß ;) " | C7: Nicht feststellbar | D7: Nicht feststellbar | E7: =IF(C7="NICHT-ANALYSIERT", "NA", IF(C7=D7, 1, 0)) -> 1
A8: 7 | B8: Kaffee kochen - ja, aber Kaffee aus normaler Materie, mit der Energie der Annihilation der Antimaterie. Und wie gesagt, das auch nur wenn man Jahrzehnte der Produktion gleichzeitig zur Verfügung hätte, was nicht der Fall ist. Eine Tasse voller Antimaterie wäre eine völlig andere Größenordnung, und würde reichen um eine Großstadt zu zerstören. -- 00:09, 10. Dez. 2013 (CET) | C8: Nicht feststellbar | D8: Nicht feststellbar | E8: =IF(C8="NICHT-ANALYSIERT", "NA", IF(C8=D8, 1, 0)) -> 1
A9: 8 | B9: Fruchtfleisch, Samen, Rinde, Blätter und Sprößlinge des Affenbrotbaums sind vielseitig einsetzbar. Sie liefern Nahrung, Wasser, Kleidung, Material zum Dachdecken, Klebstoff, Medizin, Halsschmuck, Süßigkeiten, Schnüre, Seile, Netze, Matten, Hüte, Tabletts, Kisten, Körbe, Papier, Seife, Kaffee, Bier und Öl. | C9: Nicht feststellbar | D9: Nicht feststellbar | E9: =IF(C9="NICHT-ANALYSIERT", "NA", IF(C9=D9, 1, 0)) -> 1
A10: 9 | B10: Kaffee, Madeln, Karamel und Chilli | C10: Nicht feststellbar | D10: Nicht feststellbar | E10: =IF(C10="NICHT-ANALYSIERT", "NA", IF(C10=D10, 1, 0)) -> 1
A11: 10 | B11: Sonst spende ich stets den Freundlichen Gruß. In diesem Fall bin ich ob des frisch versenkten Arbeitsaufwandes schon extrem ungehalten. Wenn das nicht haarklein aufgeklärt wird, gibt´s einen Vandalismus-Rev, und vieleicht mal einen Antrag auf Benutzersperrung, weil ich nun ziemlich den Kaffee aufhabe. OK? Gruß 19:15, 5. Jun 2005 (CEST) | C11: Maskulinum oder Neutrum | D11: Maskulinum oder Neutrum | E11: =IF(C11="NICHT-ANALYSIERT", "NA", IF(C11=D11, 1, 0)) -> 1 | F11: Definiter Artikel, den
A12: 11 | B12: Wieso hat er es sich mit Heydrich verdorben"? Hat er ihm in den Kaffee gespuckt oder war seine Bügelfalte zu lasch? " | C12: Maskulinum oder Neutrum | D12: Maskulinum oder Neutrum | E12: =IF(C12="NICHT-ANALYSIERT", "NA", IF(C12=D12, 1, 0)) -> 1 | F12: Definiter Artikel, den
A13: 12 | B13: Nach einer Definition der Weltgesundheitsorganisation gilt jede Substanz als Droge, die in einem lebenden Organismus Funktionen zu verändern vermag. Dieser erweiterte Drogenbegriff erfaßt nicht nur Cannabisprodukte, Halluzinogene, Stimulantien, Schnüffelstoffe, Schlaf- und Beruhigungsmittel, Alkohol, Tabakerzeugnisse, Schmerzmittel Opiate und Kokain. Er bezieht sich auch auf Alltagsdrogen wie z.B. Kaffee und Tee und grenzt Drogen einerseits sowie Genuß- und "Lebens"mittel andererseits nicht mehr trennscharf voneinander ab"." | C13: Nicht feststellbar | D13: Nicht feststellbar | E13: =IF(C13="NICHT-ANALYSIERT", "NA", IF(C13=D13, 1, 0)) -> 1
A14: 13 | B14: Also etwas fragwürdig finde ich es schon, wenn ein Link angebracht wird, der auf eine Seite führt, die Kaffee vermarktet, selbst wenn &#x20ac; 1,00 an eine Kirchenschule geht. Rasselas - Ein Premiumkaffee des Prinzen Asfa-Wossen Asserate von Äthiopien Soziales Projekt des Prinzen Asfa-Wossen Asserate. Ich bin noch nicht lang genug bei Wiki um eigenständig in so einem Fall zu handeln, möchte es aber diskutieren. | C14: Nicht feststellbar | D14: Nicht feststellbar | E14: =IF(C14="NICHT-ANALYSIERT", "NA", IF(C14=D14, 1, 0)) -> 1
A15: 14 | B15: Interessant wird es aber, wenn man zu experimientieren beginnt. Also: Ich bin ein klassischer Übersäuerungskandidat: Zuviel Kaffee, gerne Zucker und schlechte Kohlenhydrate und auch Schweinefleisch. Seit einiger Zeit habe ich mit Müdigkeit zu kämpfen... | C15: Nicht feststellbar | D15: Nicht feststellbar | E15: =IF(C15="NICHT-ANALYSIERT", "NA", IF(C15=D15, 1, 0)) -> 1
A16: 15 | B16: Wieso empfiehlst Du aber Kaffee zu meiden? Ich konnte bislang keine größere empirische Studie finden, die einen Zusammenhang zwischen Kaffee und Alterung bzw. Lebenserwartung aufzeigt. Gibt es Substanzen im Kaffee, die das Altern beschleunigen, z.B. freie Radikale verursachen? | C16: Maskulinum oder Neutrum | D16: Maskulinum oder Neutrum | E16: =IF(C16="NICHT-ANALYSIERT", "NA", IF(C16=D16, 1, 0)) -> 1 | F16: Im Kaffee -> Präposition mit einem bestimmten Artikel
A17: 16 | B17: Sie müssen viel telfonieren um genug Kunden und Anwerber zu finden. Sich mit diesen treffen, Kaffee ausgeben und auch mobil sein (Benzin-, Fahrgeld). Sie werden sich vermutlich auch neu einkleiden müssen, stehts ordentlich auftreten - dazu genört auch Maniküre, Kosmetiksalon, Nagelstudio was innerhalb der Amway-Riege als ganz normal &amp;gt;verkauft&amp;lt; wird. Wieder lässt sich hier eine zweigleisigkeit erkennen. Denn ihr Verlangen nach Luxusartikel ist wie bei den meisten Menschen vermutlich gut ausgeprägt. Nun bei wem werden sie ihre neue Kosmetik kaufen? Die Luxusgüter - Parfum... | C17: Nicht feststellbar | D17: Nicht feststellbar | E17: =IF(C17="NICHT-ANALYSIERT", "NA", IF(C17=D17, 1, 0)) -> 1
A18: 17 | B18: Zum Frühstück gab es üblicherweise englisches Porridge, dazu Schinken und Eier, Wurst, Brot, Tee oder Kaffee. | C18: Nicht feststellbar | D18: Nicht feststellbar | E18: =IF(C18="NICHT-ANALYSIERT", "NA", IF(C18=D18, 1, 0)) -> 1
A19: 18 | B19: @tom:?? Ich weiß jetzt zwar nicht, warum Du dich angesprochen fühlst und dich so echauffierst, denn die Erläuterug steht oben (aktiv/passiv). Wie klare Begriffe im Alltag mitunter umgangssprachlich anders interpretiert/genutzt werden, ist was anderes (z.B. Igor's Kaffee, daher z.B. auch eine DIN). Und wie schon oben geschrieben, kommt es nicht darauf an, ob jemand da sitzt, sondern in welchem Kontext diese Arbeit ausgeführt wird... -- 10:41, 27. Jan 2006 (CET) | C19: Nicht feststellbar | D19: Nicht feststellbar | E19: =IF(C19="NICHT-ANALYSIERT", "NA", IF(C19=D19, 1, 0)) -> 1
A20: 19 | B20: sing* Morning has bro-ken, like the first mor-ho-horning, blackbird has spo-ken, like the first bird.... Die kleine vorgeschlagene Ergänzung würde darüberhinaus eine wunderschöne Symmetrie in die Einleitung bringen, wir hätten dann (bei meiner Bildschirmgröße und Auflösung) drei Absätze à je fünf Zeilen. Bei euch mag die Zeilenlänge variieren, hübsch anzusehen wäre es dennoch! Schönen Sonntag euch allen, ich gehe dann erstmal einen Schneesonnen-Spaziergang machen, wenn ich meinen Kaffee geschlürft habe...-- 11:12, 12. Feb 2006 (CET) | C20: Maskulinum oder Neutrum | D20: Maskulinum oder Neutrum | E20: =IF(C20="NICHT-ANALYSIERT", "NA", IF(C20=D20, 1, 0)) -> 1 | F20: meinen Kaffee -> possessives Pronomen, Akkusativ
A21: 20 | B21: Andererseits ist die Tun"-Form nicht ausschliesslich eine Zukunftsform. "Duesch (du) dä Esu choufä?" =&amp;gt; Tust du diesen Esel kaufen? "Sii duet tuschur parlierä bem Caffee tringke." =&amp;gt; Sie tut immer(tourjours) parlieren/sprechen beim Kaffee trinken. "Dueschmer schnäu dä Bryef schribe?" =&amp;gt; Tust (du) mir schnell diesen Brief schreiben. "Duesch das itze lo sy!" =&amp;gt; Tust (du) dies jetzt lassen sein! (Imperativ ;) ) (Es wäre aber auch "Losch das itze lo sy!" (Lässt (du) dies jetzt lassen sein) möglich. Oder noch kürzer: "Los lo sy!" (Las es lassen sein) " | C21: Maskulinum oder Neutrum | D21: Maskulinum oder Neutrum | E21: =IF(C21="NICHT-ANALYSIERT", "NA", IF(C21=D21, 1, 0)) -> 1 | F21: beim -> Präposition mit einem bestimmten Artikel
A22: 21 | B22: - Anita Kehrte aber ziemlich schnell nach Breslau zurück. - Die Familie wollte zusammen bleiben. - Einwanderung nach Amerika: schwierig w/ Codesystem. - Anita wollte nach Paris - die Rettung war greifbar nah. - Sie will wieder richtig arbeiten. - Juden hatten ein &#x201e;J&#x201c; auf ihren Karten. - Juden durften nur zu bestimmten Zeiten einkaufen gehen. - Juden mussten einen gelben Stern tragen. Nach dem Polenfeldzug begann die Deportationen ernsthaft - Anita hatte eine glückliche Kindheit, mit wenig Regeln: Sie durften niemals faul herumsitzen. Sonntagnachmittag mußten alle bei Tisch sein und Kaffee trinken. - Die Familie wollte immer noch auswandern. Aber es klappte nicht. - Man zog um zur Schwester der Mutter. Dort war es sehr eng - Anita schrieb am 15.01.1941: Sie geht wieder in die Schule als Schülerin und hat in 4 Wochen 2 Schuljahre nachgeholt. - Renate schrieb: sie arbeitet bei der Müllabfuhr, ist jetzt krank. Sie musste Zahnpastatuben und Metalle aus toten Ratten aussortieren. - Anita gibt Lateinunterricht - Sie ist überall gut in der Schule - Die Schule wurde geschlossen -&amp;gt; man traf sich in den Privatwohnungen der Lehrer, um weiter zu lernen - Anita gehörte zu den 10 Besten, die an eine andere Schule verschickt wurden - Renate mußte in einer Papierfabrik arbeiten. - In dieser Fabrik arbeitete Anita später auch. - 09.04.1942 Eltern werden deportiert (die Kinder waren zu der Zeit in der Fabrik) - Die Kinder hätten auch mitkommen können. Doch der Vater wollte, dass sie zum Schutz allein zuhause blieben. - Vater schreibt Briefe und hofft, wieder zurückzukommen, Mutter sei fix und fertig, - 8. auf 9. 04.01942: Vater ruft an und wusste, dass er nicht mehr zurückkommt. Er erklärt Anita, wie man Miete und Strom zahlt. Sie durfte seine Unterschrift fälschen. Ihr Vater verließ sich auf sie. - Letzte Worte des Vaters an Anita: &#x201e;Anita, pass auf deinen Gang auf&#x201c; - Graf Kinigel wollte den Eltern helfen. Er verlangte von der Gestapo, dass der Vater freigelassen werden sollte, da man ihn brauchte. Wenn der Name noch nicht registriert sei, würde man ihn freilassen. - Anita und ihre Schwester waren auf sich allein gestellt - Bei der Großmutter, die 82 Jahre war (schwierig) und mit dem alten Ehepaar, welches schon lange Zeit, bevor sie eingezogen waren, Untermieter ihrer Tante war. - Doch ihr Onkel und ihre Tante sind schon deportiert worden - Das hieß aber nicht, daß endlich mehr Platz durch freie Zimmer entstand. Die verlassenen Räume wurden nämlich versiegelt - Die Großmutter weigert sich, das Passierte wahrzuhaben. - Anita und Renate arbeiten wieder in der Fabrik, da sie sich um die Lebensmittel kümmern mussten. - Dies war aber schwierig, da Juden nur zu bestimmten Zeiten und begrenzt einkaufen durften - Anita und Renate stahlen gebrauchte Reisemarken, die weder mit Datum, noch mit dem Namen der Besitzer, noch mit &#x201e;J&#x201c; für Jude gekennzeichnet waren. - Somit konnten sie im jeden Geschäft einkaufen - Renate ging einkaufen, da sie weniger jüdisch aussah als Anita. - Die einzigen, die sie noch haben sind Verwandte in der Schweiz (Tante Vally und Onkel Siegfried). - Anita und Renate geht es gesundheitlich nicht sehr gut da sie viel arbeiten müssen. - Die Großmutter wird deportiert, verstand aber nicht, was mit ihr passierte. Bis zum letzten Moment bewarte sie Stolz und Würde. - Nach ihrer Deportation wurde noch ein Zimmer versiegelt - Anita und Renate sollen ins Waisenhaus. Sie wollen nicht. Aber ihnen bleibt keine andere Wahl. - Das alte Ehepaar ist nämlich auch fort gegangen. - Einen verzweifelten Brief, den Anita an ihre Tante und ihren Onkel geschrieben hat, schickt die Tante an ihren Sohn Harry weiter, der Beziehungen mit Menschen an der Schweizer Grenze hatte. - Dieser hatte einen Plan, der genial aber auch vollkommen unrealistisch war: - Er wollte Anita und Renate über die Grenze in die Schweiz schmuggeln. - Anita und Renate brauchten einen Plan, ohne daß jemand es merkte, aus dem Weisenhaus zu kommen, und ohne daß andere Menschen hineingezogen wurden. - Lösung : Sie gingen angeblich zur Arbeit. - In der Papierfabrik gab es getrennte Toiletten für Juden, Polen und Deutsche. - In der Judentoilette war ein Loch in der Wand. Auf der anderen Seite waren französische Kriegsgefangene. - Sie konnten dort Botschaften austauschen und sich unterhalten. - Renate und Anita fälschten Urkunden und stellten Urlaubsscheine für französische Zivilarbeiter aus. - Dies maachten sie mit der Schreibmaschine ihres Vaters. Gestempelt wurden diese Dokumente von Leuten des Widerstandes.. - Anita und Renate machten so auch Papiere für sich. Anita hieß Madeleine Demontaigne. - Ihre Freunde Ruth und Werner Krumme begleiteten sie. Doch alle vier wurden von der Gestapo verhaftet. - Werner war Arier. Er überlebte als Häftling. Doch Ruth war Jüdin. Sie wurde vergast. - Renate und Anita hatten die Chance, zu flüchten. Sie kamen zum Bahnhof in Paris. Doch in dem Augenblick, als sie einsteigen wollten, wurden sie von der Gestapo verhaftet. - Renate hatte schon einmal Zyankali von Konrad Latte bekommen. Da sie aber nicht geflohen sind, hatte er es wieder. - Doch für Paris gab er es ihr wieder. Aber es war Puderzucker, was sie nicht wußten. - Renate und Anita wollten sich auf dem Weg von der Polizei zur Gestapo damit umbringen - Anita und Renate taten so, als ob sie Französinnen wären. - Urteil: Renate 3 ½ Jahre Zuchthaus - Anita 18 Monate Gefängnis - Es waren immer 4 Personen in einer Zelle - Die schlimmste Erinnerung war das Schlüsseldrehen im Schloss. - Auftakt zur Arbeit : Zinnsoldaten anmalen - Eine Kollegin im Gefängnis war total gegen Juden und beschimpfte sie immer : &#x201e;Du kommst in die Gaskammer.&#x201c; - Anita musste für die Soldaten an der Front Strümpfe stricken. Sie war verzweifelt, weil sie das nicht konnte. Die Frau, die für die Verteilung der Arbeit zuständig war, hatte Mitleid mit ihr und lies sie Netze machen. - Anita konnte so ihre Zeit vertreiben. Doch sie hatte mehr Eifer als alle Anderen und hatte am Ende doppelt so viele Netze wie die Anderen. Ihr wurde gedroht. Deshalb trennte sie abends alles noch einmal auf und machte die Netze noch einmal. - Anita musste zum Zahnarzt. Dort sagte ihr eine Frau, die entsetzlichen Gespräche über Auschwitz seien wahr. - Der Aufseher bestellte Anita ins Büro. Dort musste sie unterschreiben, dass sie nach Auschwitz abtransportiert wird. - Im KZ musste sie sich ausziehen. Ihr Kopf wurde rasiert, und die Nummer 69388 wurde auf ihren linken Arm tätowiert.- Anita erzählte dem Mädchen, das ihr die Haare abschnitt, dass sie Cello spielt. Daraufhin hörte sie von ihr: &#x201e;Phantastisch, Du wirst gerettet werden.&#x201c; - Anita hatte keine Ahnung, was gemeint war. Aber sie tat, was ihr gesagt wurde, und stellte sich abseits von allen Anderen. Splitternackt, mit kahlem Kopf und einer Zahnbürste in der Hand wartete sie. - Dann kam Alma Rosé (eine jüdische Geigerin). Sie war begeistert - Für Anita war das alles wie ein Traum. - Anita musste erst einmal in Quarantäne - Das Appellstehen war sehr schlimm. Es war verboten, sich zu bewegen. Das Zählen dauerte manchmal Stunden. Für Leute mit Durchfall war es besonders schlimm: Man stand da mit fürchterliche Krämpfen, während die Scheiße einem an den Beinen herunterlief &#x201e;Keiner der nicht dort war, kann sich vorstellen, wie groß unser Elend war.&#x201c; - Der SS-Offizier Hössler rief eines Tages nach der Cellistin - Er brachte sie zum Orchesterblock. Dort spielte sie den &#x201e;langsamen Satz&#x201c; aus dem Boccherini Konzert vor. - Anita wurde Mitglied des Lager-Orchesters. - Auch Leute, die keine Instrumente spielten konnten als Notenschreiber aufgenommen werden - Aufgabe: Marschmusik spielen. - Anita bekam Flechttyphus. Sie dachte, nun würde sie sterben. Aber sie überlebte und konnte weiter Cello spielen. - Es wurden Konzerte im Lager gegeben. - Anita traf plötzlich Renate wieder. - Erkennungszeichen: Die alten Schuhe von Anita, die sie der Frau gegeben hatte, die ihr die Haare abrasiert hatte. - Sie erzählten sich gegenseitig von der Zeit, in der sie getrennt gewesen waren. - Renate bekam auch Typhus, wurde aber nicht so schnell wieder gesund wie Anita. Aber sie überlebte. - Anita sorgte dafür, dass Renate als &#x201e;Läuferin&#x201c; eingesetzt wurde - -&amp;gt; Renate bekam bessere Rationen und war auf dem Weg der Besserung. - Als Läuferin wartete man darauf, Nachrichten zu übergeben.Man durfte im ganzen Lager frei herumlaufen. - Manche wurden frei gelassen. Diese hatten 1 Stunde Zeit ihre Sachen zu packen, wenn davon noch etwas übrig geblieben war. - Es entstanden Freundschaften. Alle hielten zusammen. - Im Mai 1944 kamen die Juden aus Ungarn. 24000 Ungaren wurden an einem Tag ermordet. - Keiner wusste mehr, was außerhalb des Lagers geschah. - Ende Oktober 1944 mussten sich Arier auf einer und Juden auf der anderen Seite aufstellen. - Alle dachten, es ginge zur Gaskammer. Sie stiegen in Transporter und fuhren irgendwo hin. - Sie kamen nach Bergen-Belsen. - Dies war ein kleines KZ mit &#x201e;nur&#x201c; 1000 lagerinsassen. Nun kamen 3000 hinzu. Sie hatten keinen Platz. - Die Neuankömmlinge wurden in einem Zelt untergebracht. - Am nächsten Morgen kamen alle in den Lagerraum und später in eine Baracke. - Viele starben, da sie keine Kraft mehr hatten. - Arbeit: Cellophan flechten. - Jeder erlebte Tag war wie ein Wunder. - Die Häftlinge bekamen weder Essen noch Trinken. - Alles seltsam: Immer weniger SS-Leute zu sehen - Plötzlich kamen englische Panzer: Hoffnung! - Ein Engländer sagte: &#x201e;Hier ist die britische Armee. Bitte bleibt ruhig. Wir sind gekommen, um Euch zu befreien. Verlasst nicht das Lager. Habt keine Angst. Ihr seid frei.&#x201c; - Zum Jubeln hatten sie keine Kraft mehr. - Befreiung:1 5.04.1945 um 4 Uhr nachmittags. - Die Panzer kamen drei Tage nach dem Waffenstillstand. - Durch das Fernsehen stellten sie Kontakte zu ihren Bekannten her. Sie schrieben an Marianne. - Sie bekamen wieder Essen und Trinken. - Familie und Verwandte versuchten, eine Einreisegenehmigung zu bekomme. Doch es war aussichtslos. - Sie bekamen Gelegenheit, nach Brüssel zu fahren (Dez. 1945). - (mit gefälschten Papieren. Der Versuch glückte!!) - Sie kamen bei einer Freundin aus dem KZ unter. - Sie versuchten von da aus, Papiere für England zu bekommen. - Anita konnte auch wieder Cello spielen. - 18. März 1946 Abfahrt nach England! - Der Kapitän war stolz zwei, Ex-Belsen Gefangene an Bord zu haben. - Anita wohnt bis heute in England, doch traf sie nur zweimal in ihrem Leben ihre Schwester Marianne wieder. - Sie wollte nie mehr einen Fuß auf deutschen Boden setzen!! | C22: Nicht feststellbar | D22: Nicht feststellbar | E22: =IF(C22="NICHT-ANALYSIERT", "NA", IF(C22=D22, 1, 0)) -> 1 | F22: "sein und" wird als possessives Pronomen interpretiert
A23: 22 | B23: Warum? Die eindeutige Zuordnung zur heutigen Türkei ist nicht möglich, da es offenbar im gesamten Osmanische Reich verbreitet war. Auch ist die Unterscheidung in türkischen" und "deutschen" Joghurt sehr willkürlich und wenn man so will "Deutschlandlastig". Ich weiß nicht sehr viel über Joghurtbakterien, aber es scheint hier eher um die Verwendung von Lactobacillus delbrueckii subspecies bulgaricus und Lactobacillus acidophilus zu gehen, welche zwar vieleicht national unterschiedlich stark Verwendung finden, aber keinem Kulturkreis eindeutig zuzuordnen sind. Das mit der ländlichen Türkei klingt zwar romantisch, aber kann man genauso gut mit Tee oder Kaffee ersetzen. 21:30, 5. Jun. 2008 (CEST) " | C23: Nicht feststellbar | D23: Nicht feststellbar | E23: =IF(C23="NICHT-ANALYSIERT", "NA", IF(C23=D23, 1, 0)) -> 1
A24: 23 | B24: Kaffee | C24: Nicht feststellbar | D24: Nicht feststellbar | E24: =IF(C24="NICHT-ANALYSIERT", "NA", IF(C24=D24, 1, 0)) -> 1
A25: 24 | B25: Kaffee ein Antivitamin? Auf der Seite http://www.uni-bayreuth.de/departments/didaktikchemie/umat/kaffee1/1_kaffee1.htm wird das beispielsweise widerlegt weiss jemand genaueres? Die Information auf dieser Wiki Seite sind recht dürftig | C25: Nicht feststellbar | D25: Nicht feststellbar | E25: =IF(C25="NICHT-ANALYSIERT", "NA", IF(C25=D25, 1, 0)) -> 1
A26: 25 | B26: Ich habe versucht, die Beispiele aus dem sehr guten Artikel der österreichischen Apothekerzeitung nach Wirkmechanismen zu ordnen. Beim Kaffee ist die Antivitaminwirkung eine Frage der Dosis. Normale Ernährung und normaler Kaffeegenuß führen nicht zu einer Vitaminmagnelwirkung. 12:31, 20. Apr. 2007 (CEST) | C26: Maskulinum oder Neutrum | D26: Maskulinum oder Neutrum | E26: =IF(C26="NICHT-ANALYSIERT", "NA", IF(C26=D26, 1, 0)) -> 1 | F26: beim -> Präposition mit einem bestimmten Artikel
A27: 26 | B27: Okay. Ich verstehe Deinen Punkt jetzt. Danke! Zu den häufigsten Lebensmittelquellen zählt er freilich nicht, da die wenigsten Menschen reglemäßig Granatäpfel konsumieren - im Gegensatz zu Kaffee zum Beispiel. Dennoch ist er eines der wirksamsten Antioxidantien. Du hast ihn ja schon oben in die Tabelle aufgenommen. Vielleicht könnte man ihn im Text trotzdem noch einmal erwähnen... Viele Grüße, -- 09:58, 14. Jul. 2011 (CEST) | C27: Nicht feststellbar | D27: Nicht feststellbar | E27: =IF(C27="NICHT-ANALYSIERT", "NA", IF(C27=D27, 1, 0)) -> 1
A28: 27 | B28: @Plenz: Geschwister müssen nicht die gleichen Vorlieben haben, da sich die Lernumwelt, die entscheidend für den Erwerb von Geschmackspräferenzen zu sein scheint, unterschiedlich sein kann. Andererseits wäre es auch möglich, das die Geschwister unterschiedliche Modelle wählen (Vater: Kaffee, Mutter: Tee, nur als Beispiel) oder sich die Eltern unterschiedlich ihren Kindern gegenüber verhalten. Möglich wäre, das ein Junge dafür belohnt wird, das er hochkalorische Sachen isst (damit er groß und stark wird ;-) ), ein Mädchen eventuell dafür nicht (hochkalorische Sachen können dick machen). Das würde dazu führen, das sich, aufgrund assoziativer Lernprozesse (Konditionieren) unterschiedliche Präferenzen bilden. Grüße, 19:03, 13. Apr. 2007 (CEST) | C28: Nicht feststellbar | D28: Nicht feststellbar | E28: =IF(C28="NICHT-ANALYSIERT", "NA", IF(C28=D28, 1, 0)) -> 1
A29: 28 | B29: Der Begriff Pott" ist inzwischen ähnlich dem "Tschüß" schon nicht mehr so auf Norddeutschland beschränkt wie vielleicht vor 20 Jahren. Hier in Berlin kann man neben der "Latte" inzwischen an vielen Stellen, besonders an populären Orten, normalen Kaffee im "Pott" bestellen. Dieser Sprachgebrauch ist nach meinem Eindruck Deutschlandweit im Vormarsch. " | C29: Maskulinum oder Neutrum | D29: Maskulinum oder Neutrum | E29: =IF(C29="NICHT-ANALYSIERT", "NA", IF(C29=D29, 1, 0)) -> 1 | F29: Adjektivflexion, -en
A30: 29 | B30: Liebe Barb, offenbar habe ich mit meinem Versuch, persönliche Attacken zu unterbinden, dir nur noch weiter Zucker in den Kaffee getan. Ich sehe, dass du aus der Sachdebatte gerne eine Personendebatte machen möchtest: du disqualifizierst dich selbst", "oberflächlich, "arrogant" und so weiter. Fehlen dir auf der Sachebene dermaßen die Argumente? Das ist ein Gesprächsverhalten, das ich leider vor allem von Feministinnen kenne, auch wenn sie von sich selbst behaupten, aber sowas von neutral zu sein. Selbstverständlich ist es weder oberflächlich noch arrogant, nachweisbar unsinnige Behauptungen als solche zurückzuweisen. Was also solche Herabsetzungen deinerseits angeht, halte ich es doch lieber mit dem alten Spruch, dass wenn jemand mit dem Finger auf andere zeigt, vier Finger auf ihn selbst zurückweisen. Ansonsten nehme ich mit Interesse zur Kenntnis, dass die von mir behandelten Themen (Ungleichbehandlung von Männern in Jusiz, Schule und Gesundheitswesen, männliche Opfer häuslicher Gewalt, sexueller Missbrauch durch Frauen etc.pp.) offenbar bei einigen Frauen dermaßen unerwünscht sind, dass sie solche Reaktionen der persönlichen Diskreditierung auslösen. - Arne " | C30: Maskulinum oder Neutrum | D30: Maskulinum oder Neutrum | E30: =IF(C30="NICHT-ANALYSIERT", "NA", IF(C30=D30, 1, 0)) -> 1 | F30: In den -> definiter Artikel
A31: 30 | B31: Lieber Arne, ich trinke meinen Kaffee gern schwarz. Mit der persönlichen Attacke hast du angefangen, in dem du einer anderen Diskussionsteilnehmerin ihre persönliche Qualifikation abgesprochen hast. Und machst weiter mit persönlichen Unterstellungen. Da hast du gut von den Feministinnen gelernt. In meinem zweiten Posting gehe ich auf zwei falsche Annahmen von dir ein, von denen du aber anscheinend so fest überzeugt bist, dass du eh nicht davon abzubringen bist. Es gibt den schönen Spruch: Jeder, der nicht meine Dfreund ist, ist mein Feind." bei dir wohl eher: "Jeder, der nicht meine Freund ist, ist eine Feministin." " | C31: Maskulinum oder Neutrum | D31: Maskulinum oder Neutrum | E31: =IF(C31="NICHT-ANALYSIERT", "NA", IF(C31=D31, 1, 0)) -> 1 | F31: meinen Kaffee -> possessives Pronomen, Akkusativ
A32: 31 | B32: Was hat vegane Ernährung mit Adipositas zu tun? Zuckerhaltige Limonaden wie Cola/Fanta, Pommes, Nudeln, Pizza, Kuchen, Speiseeis, Zuckerwaren, Tabak, Alkohol, Kaffee - alles vegan oder vegan möglich. Die hier genannten Ursachen zeigen dazu noch, wie vielfältig die Gründe sind, welche nicht durch eine Methode allein zu beheben sind. 15:38, 23. Mär. 2016 (CET)timestamp | C32: Nicht feststellbar | D32: Nicht feststellbar | E32: =IF(C32="NICHT-ANALYSIERT", "NA", IF(C32=D32, 1, 0)) -> 1
A33: 32 | B33: Verzweifelte Klimmzüge! LITERATUR zu: Anti-Islamismus muß her. Der Rest ist kalter Kaffee und POV auch in der Disku.-- 23:31, 25. Jul. 2007 (CEST) | C33: Maskulinum oder Neutrum | D33: Maskulinum oder Neutrum | E33: =IF(C33="NICHT-ANALYSIERT", "NA", IF(C33=D33, 1, 0)) -> 1 | F33: Adjektivflexion, -er
A34: 33 | B34: Schönen Tag mit Kaffee Hag. -- 21:36, 29. Mär. 2007 (CEST)timestamp | C34: Nicht feststellbar | D34: Nicht feststellbar | E34: =IF(C34="NICHT-ANALYSIERT", "NA", IF(C34=D34, 1, 0)) -> 1
A35: 34 | B35: denn er impliziert, daß es 1995 eine DDR gab, und das trifft nicht zu. 1995 war die DDR bereits Vergangenheit. Daher &#x201e;Ehemalige DDR&#x201c;. Oder würdest Du z. B. schreiben, daß &#x201e;gestern der Bundeskanzler Gerhard Schröder einen Kaffee trank&#x201c;? Gruß, 15:07, 29. Okt. 2007 (CET) | C35: Maskulinum oder Neutrum | D35: Maskulinum oder Neutrum | E35: =IF(C35="NICHT-ANALYSIERT", "NA", IF(C35=D35, 1, 0)) -> 1 | F35: Adjektivflexion, -en
A36: 35 | B36: In dem Wikipedia-Artikel wird behauptet, sie habe angeblich Psychologie studiert. Diese Behauptung erscheint jedoch zweifelhaft. Denn sie hat offenbar keine allgemeine Hochschulreife (kein Abitur). Über eine Höhere Handelsschule hätte sie zwar immerhin ein Fachabitur und somit den Zugang zu einem Fachhochschulstudium erreichen können. Aber erstens bieten Fachhochschulen kein Psychologie-Studium an (Psychologie ist ein universitärer Studiengang und Numerus-Clausus-Fach), und zweitens hat sie ja wohl auch keine höhere Handelsschule besucht, sondern anscheinend bloß eine einfache Handelsschule (wobei selbst da nicht feststeht, ob sie wenigstens dort denn einen erfolgreichen Abschluss erreicht hat). Anscheinend hat sie (ähnlich wie Joschka Fischer) ohne Abitur und ohne Fachhochschulreife bloß gelegentlich in Studentenwohnheimen oder studentischen Wohngemeinschaften und Uni-Mensen sowie auf Uni-Partys, und ab und zu auch in universitären Hörsäälen oder Bibliotheken herumgehangen, und in Uni-Cafeterien mit Studenten und Professoren Kaffee getrunken und mit denen ein bischen rumgelabert, aber sie hat wohl nie eine wirkliche Hochschulausbildung durchlaufen oder gar erfolgreich abgeschlossen, und schon gar nicht in der Fachrichtung Psychologie (das Numerus-Clausus-Studium der Psychologie erfolgreich zu meistern und erfolgreich abzuschließen ist zumindest an deutschen Universitäten auch gar nicht so einfach). Sie dürfte wohl eher ein Autodidakt" sein. Und Autodidakten neigen im Allgemeinen dazu, nicht streng wissenschaftlich zu arbeiten, sondern vielmehr lediglich zu den Erkenntnissen zu kommen, zu denen sie vom Ergebnis her kommen wollen. Autodidakten lernen selten eine selbstkritische unparteiische und unvoreingenommene Herangehensweise an ein Thema, sondern neigen häufig zu Voreingenommenheit und Parteilichkeit. -- 23:31, 13. Feb. 2012 (CET)timestamp " | C36: Nicht feststellbar | D36: Nicht feststellbar | E36: =IF(C36="NICHT-ANALYSIERT", "NA", IF(C36=D36, 1, 0)) -> 1
A37: 36 | B37: Zitat aus Brasilien:Mit großen, gut entwickelten Landwirtschafts-, Bergbau-, Produktions-, und Dienstleistungssektoren auf der einen Seite und einem großen Vorrat an Arbeitskräften auf der anderen ist die brasilianische Wirtschaft die kräftigste Südamerikas und gewinnt auf dem Weltmarkt an Bedeutung. Die wichtigsten Exportprodukte sind Kaffee, Kakao, tropische Früchte, Sojabohnen und Eisenerz. 40 % der brasilianischen Agrarausfuhren gehen in die EU, 17 % in die USA. Zu den größten Herausforderungen für die brasilianische Wirtschaft zählen nach wie vor die Inflation und die Kluft zwischen einer wohlhabenden, gut ausgebildeten Bevölkerungsminderheit und der schlecht ausgebildeten Mehrheit, die größtenteils am Rande des Existenzminimums lebt. Es gibt eine große Bewegung von Landlosen, die Movimento dos sem terra, die für eine Landreform kämpfen. | C37: Nicht feststellbar | D37: Nicht feststellbar | E37: =IF(C37="NICHT-ANALYSIERT", "NA", IF(C37=D37, 1, 0)) -> 1
A38: 37 | B38: Ich würde als Lösung vorschlagen, dass Dir mal einen ruhigen Nachmittag machst, vielleicht etwas Kaffee mit vor den PC nimmst und den Artikel einmal komplett von oben bis unten abschreibst. Vorher ein paar Mal durchlesen (nicht zu oft, sonst bleiben die Sätze so hängen) und dabei darauf achtest, wo Du aus der Kurve fliegst. Alternativ kann ich Dir anbieten, dass für Dich zu machen. Vielleicht mögen außer mir ja auch noch andere Menschen Texte, die nicht nur informativ sind, sondern sich auch angenehm vom Anfang bis zum Ende lesen lassen. Ein Kriterium bei den Auszeichnungen ist es jedenfalls :-) In der Hoffnung, Dir zumindest irgendwie geholfen zu haben, 21:05, 22. Jul. 2010 (CEST) | C38: Nicht feststellbar | D38: Nicht feststellbar | E38: =IF(C38="NICHT-ANALYSIERT", "NA", IF(C38=D38, 1, 0)) -> 1
A39: 38 | B39: Also bitte, Kaffee / Tee / Kakao für lau kompensiert ja wohl kein geringes Gehalt. Die Aktion mit den Stückchen ist gut, ja, allerdings kriegt man das auch nur zur Frühschicht ab (in denen der vorbildliche Student sich in einer Vorlesung aufhält..). Die Zuschüsse / Rabatte zu diversen Mittagsessen hielten sich ebenfalls stark in Grenzen. Mein gesicherter" Mitarbeiterparkplatz unterschied sich nicht nennenswert von dem Zustand eines Feldweges. Ich möchte da nun nicht weiter darauf eingehen, aber in meiner Zeit habe ich festgestellt, dass ein Großteil der Angestellten "entsprechend ihrem Lohn motiviert" arbeiten. Mit einem besseren Gehalt könnte man automatisch mehr von den Leuten erwarten (schon bei der Einstellung). Aber sie beschäftigen lieber einen Haufen unzuverlässiger Leute, die wo es nur geht bei der verrichteten Arbeit und der Arbeitszeit beschei**en. -- 22:46, 19. Sep. 2010 (CEST) " | C39: Nicht feststellbar | D39: Nicht feststellbar | E39: =IF(C39="NICHT-ANALYSIERT", "NA", IF(C39=D39, 1, 0)) -> 1
A40: 39 | B40: Offenbar hatte ich zuwenig Kaffee intus. Danke. -- 08:27, 20. Sep. 2007 (CEST) | C40: Nicht feststellbar | D40: Nicht feststellbar | E40: =IF(C40="NICHT-ANALYSIERT", "NA", IF(C40=D40, 1, 0)) -> 1
A41: 40 | B41: Stimmt ich erinnere mich. Im Zuge des Bearbeitens ist mir irgendwie die Maus von selbst davon gelaufen (nicht ganz , ich war dabei einen Kaffee zu machen, und war beim Zurückkommen ungeschickt) hab dann aber die Stelle nicht gefunden. Sorry, hätte ja auch in die Versionsführung schauen können. Aber zum Artikel: Die energie, links und Listen anzulegen, die haben sie alle, aber sich hinzusetzen und ein Exzerpt zu erarbeiten, das ist vielen zuviel. -- 19:03, 17. Apr 2006 (CEST) | C41: Maskulinum oder Neutrum | D41: Maskulinum oder Neutrum | E41: =IF(C41="NICHT-ANALYSIERT", "NA", IF(C41=D41, 1, 0)) -> 1 | F41: Indefiniter Artikel -> en
A42: 41 | B42: Damit ein Mitarbeiter im Medizinischen Bereich mitarbeiten kann braucht er die Ausbildung eines Rettungssanitäters mit aufrechtem RS-Status. Für Mitglieder gilt lt. den Satzungen: Sie müssen aktiv im Verein mitarbeiten." Das heißt im Prinzip wenn jemand Kaffee und Kuchen macht ist dieser Punkt schon erfüllt --&amp;gt; Daher ist eine RS Ausbildung nicht zwingend! -- 11:57, 18. Jan. 2009 (CET) " | C42: Nicht feststellbar | D42: Nicht feststellbar | E42: =IF(C42="NICHT-ANALYSIERT", "NA", IF(C42=D42, 1, 0)) -> 1
A43: 42 | B43: Was .en machen, interessiert uns hier nicht. Ob er Vegetarier war, interessiert nicht. Er war kein Tierrechtler oder vergleichbarer Politiker, bei dem sowas von Belang ist. Allenfalls ein kurzer Satz wäre vorstellbar. Es steht ja auch nicht in Politikerartikeln, wenn sie Nichtraucher sind, keinen Kaffee mögen oder bei offenem Fenster schlafen. -- 17:31, 2. Apr. 2008 (CEST) | C43: Maskulinum oder Neutrum | D43: Maskulinum oder Neutrum | E43: =IF(C43="NICHT-ANALYSIERT", "NA", IF(C43=D43, 1, 0)) -> 1 | F43: Negationsartikel -> en
A44: 43 | B44: Klar. Ich bin aber erst seit einer guten halben Stunde wach und noch beim ersten Kaffee. Ich habe Dir sogar geschrieben, wo Du suchen sollst. Dass Du seit drei Jahren mit unbelegten Angaben leben kannst unterstreicht nicht gerade die Dringlichkeit Deines Anliegens. Im Gegensatz zu Dir verfolge ich aber keine politische Agenda in diesem Artikel, mich stört nicht nur diese eine Stelle, sondern Qualitätsmängel, die sich durch den ganzen Artikel ziehen. -- 11:07, 14. Apr. 2017 (CEST) | C44: Maskulinum oder Neutrum | D44: Maskulinum oder Neutrum | E44: =IF(C44="NICHT-ANALYSIERT", "NA", IF(C44=D44, 1, 0)) -> 1 | F44: Adjektivflexion, en
A45: 44 | B45: regelmäßige veranstaltung in fließtext gießen, nicht nur ein satz sondern auch ein bissel mit leben füllen außerdem funkensonntag und st. ulrichstag mit datum aufführent Obwohl ich nicht recht weiß wie ich das weiter ausfüllen soll. Obs im Pfarrheim dann Kaffee und Kuchen gibt und davor nen Bierzelt steht is doch nicht wirklich relevant oder? | C45: Nicht feststellbar | D45: Nicht feststellbar | E45: =IF(C45="NICHT-ANALYSIERT", "NA", IF(C45=D45, 1, 0)) -> 1
A46: 45 | B46: Craving bezeichnet ein (nahezu unwiderstehliches) starkes Verlangen nach der Einnahme eine Substanz (vergl. Soyka, 1997) wobei dieser "Suchtdruck" auch auf nicht substanzgebundes Suchtverhalten übertragen wird. Der Begriff "Craving" wird fälschlicherweise auch gelegentlich mit dem Ausdruck "Entzug" gleichgesetzt. Jedoch beschreibt vereinfacht gesagt der Begriff "Entzug" Zustände der süchtigen Person, die dann auftreten, wenn die Substanz nicht eingenommen wird. Dazu gehören neben körperlichen Entzugserscheinungen (z.B. Zittern, Schwitzen, körperliche Unruhe) auch psychische Symptome (z.B. Reizbarkeit und Nervosität). Unter dem Begriff Craving werden jedoch nicht nur die Entzugserscheinungen subsummiert, sondern auch die mit der Substanzeinnahme antizipierte Wirkung einer Droge. Eine süchtige Person, die einen Suchtdruck verspürt, hat also gewisse Erwartungen an die Wikungen der Droge, die weit über die Linderung der Entzugssymptome hinausgehen können. So trinken z.B. Alkoholabhängig nicht nur, um Entzugserscheinungen zu begegnen, sondern auch, um sich selbstsicherer und körperlich attraktiver zu fühlen, um sich als geselliger zu erleben, oder um gewisse Probleme zu vergessen. Mit anderen Worten: Das Verlangen nach der Einnahme einer Substanz kann nicht nur dann außerodentlich stark sein, um Entzugsymptomen bei Nichtkonsum vorzubeugen, sondern der Suchtdruck kann mindestens ebenso stark ausgeprägt sein durch die mit der Einnahme einer Substanz verbundene positive Erwartung des Konsumenten. Gerade diese psychologischen Wirkungserwartungen sind überdauernder als körperliche Entzugerscheinungen und spielen ein wesentliche Rolle für Rückfälle, d.h. einen erneuten Konsum einer Droge nach einer Phase der Abstinenz. Craving unterliegt stärker einem Lernprozeß als die Entwicklung von Entzugerscheinungen, die ihrerseits deutlicher von der Dosis und der Dauer der Substanzeinnahme abhängen. So lernt ein süchtiger Patient bestimmte situative Faktoren mit der Einnahme einer Substanz zu verknüpfen (z-B. "Partybesuch" als Auslöser für Alkoholkonsum), die dann als Schlüsselreize für das süchtige Verhalten fungieren. Die Einnahme vieler Substanzen ist an solche Schlüsselreize mehr oder minder gebunden: So berichten viele Raucher, dass sie nach dem Essen zu einer Tasse Kaffee ein enormes Verlangen nach einer Zigarette verspüren, und das unabhängig davon, wie lange der letzte Noctinkonsum zurückliegt (also unabhängig vom aktuellen Blutnicotingehalt). Kommt eine süchtige Person in eine entsprechende Situation, kann sich folglich ein Suchtdruck einstellen (Craving), ohne dass physiolopgische Anzeichen für Entzugsymptome vorliegen." (Pritzel, Monika, Gehirn und Verhalten, 2009) " | C46: Nicht feststellbar | D46: Nicht feststellbar | E46: =IF(C46="NICHT-ANALYSIERT", "NA", IF(C46=D46, 1, 0)) -> 1
A47: 46 | B47: Überspitzt: Es ist also gleich, ob ich morgens eine Tasse Kaffee trinke oder mir weißen Stoff in die Adern spritze. | C47: Nicht feststellbar | D47: Nicht feststellbar | E47: =IF(C47="NICHT-ANALYSIERT", "NA", IF(C47=D47, 1, 0)) -> 1
A48: 47 | B48: Craving bezeichnet ein (nahezu unwiderstehliches) starkes Verlangen nach der Einnahme eine Substanz (vergl. Soyka, 1997) wobei dieser "Suchtdruck" auch auf nicht substanzgebundes Suchtverhalten übertragen wird. Der Begriff "Craving" wird fälschlicherweise auch gelegentlich mit dem Ausdruck "Entzug" gleichgesetzt. Jedoch beschreibt vereinfacht gesagt der Begriff "Entzug" Zustände der süchtigen Person, die dann auftreten, wenn die Substanz nicht eingenommen wird. Dazu gehören neben körperlichen Entzugserscheinungen (z.B. Zittern, Schwitzen, körperliche Unruhe) auch psychische Symptome (z.B. Reizbarkeit und Nervosität). Unter dem Begriff Craving werden jedoch nicht nur die Entzugserscheinungen subsummiert, sondern auch die mit der Substanzeinnahme antizipierte Wirkung einer Droge. Eine süchtige Person, die einen Suchtdruck verspürt, hat also gewisse Erwartungen an die Wikungen der Droge, die weit über die Linderung der Entzugssymptome hinausgehen können. So trinken z.B. Alkoholabhängig nicht nur, um Entzugserscheinungen zu begegnen, sondern auch, um sich selbstsicherer und körperlich attraktiver zu fühlen, um sich als geselliger zu erleben, oder um gewisse Probleme zu vergessen. Mit anderen Worten: Das Verlangen nach der Einnahme einer Substanz kann nicht nur dann außerodentlich stark sein, um Entzugsymptomen bei Nichtkonsum vorzubeugen, sondern der Suchtdruck kann mindestens ebenso stark ausgeprägt sein durch die mit der Einnahme einer Substanz verbundene positive Erwartung des Konsumenten. Gerade diese psychologischen Wirkungserwartungen sind überdauernder als körperliche Entzugerscheinungen und spielen ein wesentliche Rolle für Rückfälle, d.h. einen erneuten Konsum einer Droge nach einer Phase der Abstinenz. Craving unterliegt stärker einem Lernprozeß als die Entwicklung von Entzugerscheinungen, die ihrerseits deutlicher von der Dosis und der Dauer der Substanzeinnahme abhängen. So lernt ein süchtiger Patient bestimmte situative Faktoren mit der Einnahme einer Substanz zu verknüpfen (z-B. "Partybesuch" als Auslöser für Alkoholkonsum), die dann als Schlüsselreize für das süchtige Verhalten fungieren. Die Einnahme vieler Substanzen ist an solche Schlüsselreize mehr oder minder gebunden: So berichten viele Raucher, dass sie nach dem Essen zu einer Tasse Kaffee ein enormes Verlangen nach einer Zigarette verspüren, und das unabhängig davon, wie lange der letzte Noctinkonsum zurückliegt (also unabhängig vom aktuellen Blutnicotingehalt). Kommt eine süchtige Person in eine entsprechende Situation, kann sich folglich ein Suchtdruck einstellen (Craving), ohne dass physiolopgische Anzeichen für Entzugsymptome vorliegen." (Pritzel, Monika, Gehirn und Verhalten, 2009) " | C48: Nicht feststellbar | D48: Nicht feststellbar | E48: =IF(C48="NICHT-ANALYSIERT", "NA", IF(C48=D48, 1, 0)) -> 1 | F48: Wiederholung eines anderen Beitrags im Korpus.
A49: 48 | B49: Die geäußerte Kritik erscheint somit m.E. insgesamt unseriös. Sie ist sogar m.E. ebenso absurd wie der Versuch, einen Einwand damit zu entkräften, daß jemand &#x201e;prinzipiell gegen einen&#x201c; sei. Ist es nicht vielleicht genau umgekehrt? Ist diese &#x201e;Art von eigenartiger Genauigkeit&#x201c; etwa nur bei anderen anzumahnen, im eigenen Fall der &#x201e;Systematik&#x201c; (siehe den letzten Punkt) und der Abgrenzbarkeit von psychischen Krankheiten aber nach dem Wischi-waschi Prinzip zu vernachlässigen? Ich denke, daß der psychiatrische Krankheitsbegriff und die damit verbundene Pathologisierung (z.B. Unverständlichkeit der Psychose) schon problematisch genug sind. Wenn man schon neue psychiatrische Etikettierungen und Bezeichnungen &#x201e;als fest definierte Störung im DSM und im ICD&#x201c; ansieht, so sollte deren Abgrenzbarkeit zumindest untereinander mit aller kategorischen Deutlichkeit zutage treten. Sonst kann man den Quatsch ja auch lassen. Ist alles eh nur die gleiche Soße und eh nur der gleiche Brei von Medikamenten, auch wenn sie viele neue Namen haben. Es ist eh nur derselbe Kaffee wie bei der Schizophrenie auch: Erblichkeit, erblich, Erblichkeit, Krankheit, krank, Krankheit. So braucht man sich ja doch wenigstens doch keine unnötige Mühe der Verstellung mehr zu geben. | C49: Maskulinum oder Neutrum | D49: Maskulinum oder Neutrum | E49: =IF(C49="NICHT-ANALYSIERT", "NA", IF(C49=D49, 1, 0)) -> 1 | F49: derselbe -> wird als Adjektivflexion interpretiert
A50: 49 | B50: Da ich immer mit leichten Gewichtsproblemen zu kämpfen hatte, verwende ich fast ausschließlich Lebensmittel mit Süßstoffen. Cola Light, Puddings, Eis ( ausser an der Eisdiele )... also alles was geht... nur in Kaffee kommt noch Zucker :-). Unter 2 Litern Cola Light/Zero läuft auch nix. Kalorienhaltige Getränke kommen mir eh nicht ins Haus... sind mir die Kalorien zu Schade für :-). Und ich für meinen Teil habe höchstens ein Mal im Jahr Kopfschmerzen, bin dieses Jahr im Alter von 36 Jahren Vater geworden... selbstverständlich ohne Hodenkrebs :-) und habe auch sonst keine Auswirkungen von Süßstoffen feststellen können. | C50: Nicht feststellbar | D50: Nicht feststellbar | E50: =IF(C50="NICHT-ANALYSIERT", "NA", IF(C50=D50, 1, 0)) -> 1
A51: 50 | B51: ...Ja, und das Ergebnis der Liason soll Jean Loret gewesen sein. Das ist kalter Kaffee und nach neuerer Forschung mit ziemlicher Sicherheit Unsinn.-- 13:52, 28. Feb. 2012 (CET)timestamp | C51: Maskulinum oder Neutrum | D51: Maskulinum oder Neutrum | E51: =IF(C51="NICHT-ANALYSIERT", "NA", IF(C51=D51, 1, 0)) -> 1 | F51: Adjektivflexion, er
A52: 51 | B52: OK, Moment mal. Vor wenigen Minuten habe ich noch friedlich schlummernd im Bett gelegen. Das war wohl etwas zu hektisch, und noch kein Kaffee: ich schreibe gerade ein Review zu einem Review. Das mit der Familie ist schon richtig, mit solchen abenteuerlichen Flexionen ärgern wir Deutschen die Franzosen (de la famille) und Engländer (of the family). Wir Hunnen nennen das Wunderwaffe, und es ist unsere Vergeltung für die französischen und englischen Präpositionen. Und ich lese jetzt erst einmal einen Kaffee und schütte mir den Artikel in den Hals. -- 13:08, 31. Mär. 2014 (CEST)timestamp | C52: Maskulinum oder Neutrum | D52: Maskulinum oder Neutrum | E52: =IF(C52="NICHT-ANALYSIERT", "NA", IF(C52=D52, 1, 0)) -> 1 | F52: Negationsartikel -> Ø
A53: 52 | B53: Zur Pseudowissenschaft: Das ist Astrologie nur dann, wenn sie den Anspruch einer Wissenschaft erhebt. Das macht sie aber nicht immer, sondern autorenweise und nur gelegentlich. Astrologen wissen selbst, dass ihre Arbeit psychologisch funktioniert und nur wenige versuchen erfolglos den Aberwitz, sich mit Wissenschaftlichkeit" zu rechtfertigen. Das ist eher so ein Randphänomen, an dem sich dann die ernsthafte Fachwelt hochzieht, weil man damit die Astrologie gut bloß stellen kann. Im Prinzip wartet doch jeder von uns nur auf die nächste "astrologische Studie", um sich dann über deren Methoden lustig zu machen und vor Freude auf die Schenkel zu klopfen. Das sind so Witze am Rande. In jeder Wissenschaft gibt es nen Pausenclown für die Weblektüre zwischendurch. Und die Astronomie hat eben auch einen. Man liest es, man lacht mal kurz, dann trinkt man ne Tasse Kaffee und dann ist es wieder vorbei. Man muss das nicht unbedingt bierernst nehmen. :) " | C53: Nicht feststellbar | D53: Nicht feststellbar | E53: =IF(C53="NICHT-ANALYSIERT", "NA", IF(C53=D53, 1, 0)) -> 1
A54: 53 | B54: In der Tat war ich im Urlaub und auch in Almeria. Gerne kannst Du mich auch besuchen, puppe" offeriert Dir sogar einen Kaffee, doch nur eine Frage, was hat dies mit ADHS zu tun??? Nochmals lieber Garfield, richte Deine Fragen betreffend Existenz und dessen Seriösität doch direkt an Herrn J.Schmid!! Oben siehst Du sogar seine E-Mail Adresse, falls Du sie in Deiner Recherge nicht gefunden hast. " | C54: Maskulinum oder Neutrum | D54: Maskulinum oder Neutrum | E54: =IF(C54="NICHT-ANALYSIERT", "NA", IF(C54=D54, 1, 0)) -> 1 | F54: Indefiniter Artikel -> en
A55: 54 | B55: Okay Zahlendreher, warum so Böse? Ich mache das da rein, sage ich doch. Ich will den Kaffee nicht aufwärmen. Wie Du schreibst: ungenehmigte Produktion - so wie ich es auch nannte. Rumors" damals aber auch: Diepgen gegen Schwarz-Schiling... Uns so weiter und so fort. Also, ich schreibe da einen Satz dazu rein und verlinke den Spiegel-Link - Why not :-) dann ist es vollständiger und das ist doch ein akzeptabler Grund. " | C55: Maskulinum oder Neutrum | D55: Maskulinum oder Neutrum | E55: =IF(C55="NICHT-ANALYSIERT", "NA", IF(C55=D55, 1, 0)) -> 1 | F55: den -> definiter Artikel
A56: 55 | B56: DerHandelsreisende: der Vers hat mit den Muslimen im Grunde nichts zu tun. Es handelt sich dabei um eine Anweisung Mohammeds an die Banu Quraiza, die um Regelungen zwischen sich und den Banu n-Nadir baten (damals herrschte noch Eintracht zwischen Mohammed und den Juden). Geschickt verwies somit Mohammed auf die Thora. Die Exegese behandelt den Vers min. auf 5-6 gedruckten Seiten. Nur: der Vers ist auch im islamischen Recht von Belang: denn dort wählt man das Blutgeld (wenn auch nicht in allen Fällen) und nicht unbedingt qisas (talio). Was oben von diesem AL steht ist absolut kalter Kaffee. Das nenn ich Korankenntnis und Koranverständnis - zum Abwinken ist es.-- 12:33, 7. Jun. 2007 (CEST) | C56: Maskulinum oder Neutrum | D56: Maskulinum oder Neutrum | E56: =IF(C56="NICHT-ANALYSIERT", "NA", IF(C56=D56, 1, 0)) -> 1 | F56: Adjektivflexion, er
A57: 56 | B57: Danke der Nachfrage. Habs mal umformuliert. Das oder" hat im Deutschen bei Aufzählungen nicht unbedingt eine alternative Bedeutung und kann vielmehr bei Aufzählung auch Gleichrangigkeit bedeuten. "Sonntags gingen sie angeln oder schwimmen oder tranken Kaffee und Kuchen oder machten einen deutschen und islamischen Sonntagsspaziergang."-- 23:35, 27. Jun. 2007 (CEST) " | C57: Nicht feststellbar | D57: Maskulinum oder Neutrum | E57: =IF(C57="NICHT-ANALYSIERT", "NA", IF(C57=D57, 1, 0)) -> 0 | F57: tranken wird als Adjektivflexion interpretiert
A58: 57 | B58: Mediatus: in dieser illustren Gesellschaft habe ich nichts mehr zu sagen. Das ist alles kalter Kaffee, der immer wieder neu aufgegossen wird. Islamverbände sind hier keine Norm. Sie sind Nix. mit X. Es bleibt dabei: den Artikel als antiislamisch gegen den Islam" gerichtet zu bezeichnen, belegt die Unkenntnis der Dinge. Und dann die ganze de:WP in den Dreck zu ziehen nach Art des Islamisten baltext(siehe meine gelben Seiten), dem sich in silentio (!) offenbar auch andere anschließen... Nöö...mit denen nicht, danke.-- 20:52, 19. Aug. 2007 (CEST) " | C58: Maskulinum oder Neutrum | D58: Maskulinum oder Neutrum | E58: =IF(C58="NICHT-ANALYSIERT", "NA", IF(C58=D58, 1, 0)) -> 1 | F58: Adjektivflexion, er
A59: 58 | B59: Die Sockenpuppen-Diskussion ist müssig. Hier sollen Inhalte diskutiert werden, nicht persönliche Feindschaften gepflegt werden. ICH bin immer noch bereit sowohl mit Bender oder auch mit Athenaios gemütlich bei einer Tasse Kaffee den Sachverhalt in Augenschein zu nehmen. Habe deshalb diesen Absatz, Zzz-ein fake account?"und "Athenaios und sein Spiegelbild Thorwald C. Franke" (Benutzerkonten sind nun mal anonym, feindliche Outing-Versuche sind unethisch) gelöscht und bitte darum, in Zukunft darauf zu verzichten. Das Thema hier ist ATLANTIS. 18:52, 18. Dez. 2006 (CET) " | C59: Nicht feststellbar | D59: Nicht feststellbar | E59: =IF(C59="NICHT-ANALYSIERT", "NA", IF(C59=D59, 1, 0)) -> 1
A60: 59 | B60: Hier wird mal wieder die sprachliche Unkenntnis einiger Wirte zur Spezialität hochstilisiert. Nicht der Kaffee ertrinkt, sondern etwas im Kaffee. | C60: Maskulinum oder Neutrum | D60: Maskulinum oder Neutrum | E60: =IF(C60="NICHT-ANALYSIERT", "NA", IF(C60=D60, 1, 0)) -> 1 | F60: Definiter Artikel, der
A61: 60 | B61: Ja, zuerst war der italienische Affogato al caffè (der &#x201e;Ersoffene/Untergetauchte mit Kaffee&#x201c;), dann wurde er zu Affogato abgekürzt, dieser wurde wiederum außerhalb Italiens rezipiert, wobei man sich wohl gefragt hat, wo denn der Kaffee in der Bezeichnung bleibt, und so wurde aus Affogato wiederum der Espresso Affogato (der &#x201e;ertrunkene Kaffee&#x201c;). Gibt's für solche sprachlichen Staffellauf-Mutationen eigentlich keinen Fachbegriff? :-) 19:23, 30. Aug. 2010 (CEST) | C61: Maskulinum oder Neutrum | D61: Maskulinum oder Neutrum | E61: =IF(C61="NICHT-ANALYSIERT", "NA", IF(C61=D61, 1, 0)) -> 1 | F61: Definiter Artikel, der
A62: 61 | B62: Zusätzlich zum AeroPress wird eine Tasse oder eine Kanne benötigt" ==&amp;gt; und anderer Kaffee wird direkt aus der Maschine getrunken? " | C62: Maskulinum oder Neutrum | D62: Maskulinum oder Neutrum | E62: =IF(C62="NICHT-ANALYSIERT", "NA", IF(C62=D62, 1, 0)) -> 1 | F62: Adjektivflexion, er
A63: 62 | B63: Der mit dem AeroPress bereitete Kaffee kühlt sehr schnell ab." ==&amp;gt; bitte genauer erklären, verändert die Aeropress den Wärmeübergangskoeffizienten zwischen Kaffee und Luft bzw. Tasse, oder wird die Wärmekapazität herabgesetzt? " | C63: Maskulinum oder Neutrum | D63: Femininum | E63: =IF(C63="NICHT-ANALYSIERT", "NA", IF(C63=D63, 1, 0)) -> 0 | F63: Adjektivflexion, e (der ... bereitete Kaffee)
A64: 63 | B64: Hoffentlich nicht. Aber man hat mit Aeropress eben keine Kanne mehr, sondern nur den Kaffee in der Tasse. Coffee to go. Ist halt cool. -- 10:53, 19. Mär. 2013 (CET)timestamp | C64: Maskulinum oder Neutrum | D64: Maskulinum oder Neutrum | E64: =IF(C64="NICHT-ANALYSIERT", "NA", IF(C64=D64, 1, 0)) -> 1 | F64: Definiter Artikel, den
A65: 64 | B65: Tja, am Ostermontag hättest Du sie in Saarbrücken selbst fragen können: Kaffee mit Alice... Aber wende Dich doch an ihr Büro: Homepage, unter Kontakt. Ist doch sicher eine nette Erinnerung. War das zu Zeiten von Überzwerg"? -- 21:53, 2. Mai 2011 (CEST) " | C65: Nicht feststellbar | D65: Nicht feststellbar | E65: =IF(C65="NICHT-ANALYSIERT", "NA", IF(C65=D65, 1, 0)) -> 1
A66: 65 | B66: Global Fishs Verwunderung ist verständlich, ich hatte die gleichen Gedanken, als ich die Enthüllungen" las. Die Behauptung, Merkel sei in ihrer FDJ-Grundorganisation (oder wie das hieß), die vermutlich etwa 20 Personen umfasst haben dürfte, für "Agitation" und damit für so weltbewegende Dinge wie die Gestaltung der Wandzeitung u.ä. zuständig gewesen, ist in der Tat kalter Kaffee. Es muss auch gar nicht so sein, dass sich diese Funktion mit ihrer Erinnerung, sie habe sich um "Kultur" gekümmert, ausschließt. Ich vermute mal, dass man das alles an der Akademie ohnehin nicht sonderlich ernst genommen hat und dort - wie das ja auch bei der Pionierorganisation der Fall war &#x2013; überhaupt nicht oder nur allerpflichtschuldigst "agitiert" wurde (jedenfalls nicht durch die ehrenamtlichen Kräfte in der Untergruppe), sondern eben irgendwelche Freizeitveranstaltungen organisiert wurden. Wer sich jetzt über Merkels FDJ-Mitgliedschaft mokiert, der sei daran erinnert, dass in den 80er Jahren 80 Prozent aller Jugendlichen Mitglied der FDJ waren. Ohne FDJ-Mitgliedschaft war in jener Zeit de facto weder höhere Schulbildung noch ein Universitätsstudium möglich. " | C66: Maskulinum oder Neutrum | D66: Femininum | E66: =IF(C66="NICHT-ANALYSIERT", "NA", IF(C66=D66, 1, 0)) -> 0 | F66: Tat + kalter wird als Adjektivflexion Genitiv interpretiert
A67: 66 | B67: no:Rusmiddel (dt. Drogen) nennt da vor allem Kaffee und Zigaretten. Die PTA meines Vertrauens zählt Pfefferminzblätter u. dgl. auch noch dazu. -- 17:38, 14. Aug. 2011 (CEST) | C67: Nicht feststellbar | D67: Nicht feststellbar | E67: =IF(C67="NICHT-ANALYSIERT", "NA", IF(C67=D67, 1, 0)) -> 1 | F67: Vor allem wird als Adjektivflexion interpretiert
A68: 67 | B68: Dass da vor allem Kaffee und Zigaretten genannt werden, ist schlicht falsch. Tipp: Nicht nur Bilder anschauen. -- 17:49, 14. Aug. 2011 (CEST) | C68: Nicht feststellbar | D68: Nicht feststellbar | E68: =IF(C68="NICHT-ANALYSIERT", "NA", IF(C68=D68, 1, 0)) -> 1 | F68: Vor allem wird als Adjektivflexion interpretiert
A69: 68 | B69: Jedenfalls: Auch für Breivik gelten die Menschenrechte. Das bedeutet, dass im Prozess Dinge zur Sprache kommen dürfen, die nicht für die Öffentlichkeit, und deren Sensationsgier bestimmt sind. Wenn sich div. Medien nicht dran halten, so ist das ihr Kaffee. (Und ich kann mir gut vorstellen, dass seine Anwälte dies beobachten, und gegebenerzeit dagegen vorgehen; in Österreich passierte das in einigen Fällen.) Ich beziehe mich auch auf: Zulässigkeit von Äußerungen in der Berichterstattung. 11:45, 26. Apr. 2012 (CEST) | C69: Maskulinum oder Neutrum | D69: Maskulinum oder Neutrum | E69: =IF(C69="NICHT-ANALYSIERT", "NA", IF(C69=D69, 1, 0)) -> 1 | F69: ihr ->possessives Pronomen
A70: 69 | B70: Da zählt jetzt auch Milchprodukte und Kaffee zu... also sind Molkereiunternehmen Landhändler ? Ich bitte deine Quellen auch mal zu lesen !! -- 07:18, 12. Jan. 2017 (CET) | C70: Nicht feststellbar | D70: Nicht feststellbar | E70: =IF(C70="NICHT-ANALYSIERT", "NA", IF(C70=D70, 1, 0)) -> 1
A71: 70 | B71: Phoronix hat die Multithreading-Fähigkeit untersucht. Zu diesem Zweck nimmt man natürlich Software, die sich gut parallelisieren lässt. Mit aktuellen Algorithmen ist es eine Utopie jegliche Probleme dermaßen gut zu Parallelisieren und auch mit zukünftigen Algorithmen kann man nicht alles parallelisieren. Wenn du dir Kaffee machst, kannst du ja auch nicht Wasser vorwärmen, bevor du es in die Kaffeemaschine eingegossen hast. Manches muss eben sequentiell erfolgen und kann nicht parallelisiert werden. Alles zu parallelisieren ist eine unerreichbare Utopie und hat nix mit Linux oder Windows zu tun. -- 22:36, 15. Nov. 2011 (CET) | C71: Nicht feststellbar | D71: Nicht feststellbar | E71: =IF(C71="NICHT-ANALYSIERT", "NA", IF(C71=D71, 1, 0)) -> 1
A72: 71 | B72: Henriette, hab ich irgendwelche Ansprüche an die Art der Quellen gestellt? Im Fachbereich reichen doch für gewöhnlich sogar halbwegs anständige Kochbücher. Nur ein Erlebnisbericht eines einzelnen Soldaten ist mir dann doch zu wenig. Und wenn ein Weblink (Nr.2) das Teil im Museum zeigt, mit einem anderen Namen, frage ich mich auch, was nun richtig ist. Was Synonym, und was meistverbreiteter Begriff. Behelfstauchsieder gabs und gibts in Armeen, Gefängnissen, Notlagern jedweder Art, und auch einfach in unterversorgten Gebieten. Ob die Verwendung nun legal oder illegal ist, das spielt dabei keine Rolle. Genausowenig wie Beobachtungen hinsichtlich verwendeter Metallsorten und Angaben, wie schnell das Wasser kocht. Auch der Zweck ist eigentlich egal, ob nun für Kaffee, Tee, Kaffeeersatz oder zum Waschen und Rasieren. Und nun mein POV - ich kenn Erzählungen von Ex-Soldaten, dass gerade das Rasieren ein Problem war. Wenn man Ausgang bekam, war es eine verbreitete Schikane, bei Soldaten das Ergebnis per Wattetest zu kontrollieren. Bei starkem Bartwuchs half da nur Nassrasur, auch angesichts der schlechten Qualität von DDR-Trockenrasierern. Nur das Problem bei Nassrasur, man braucht heißes Wasser. In ner Kaserne ohne Fernwärme ein Problem, wenn nach dem Duschen die Kessel leer waren. Da wurde das so erzeugt. So gibts sicher diverse Sichtweisen, die noch nach Standort und Einheitstyp unterschieden werden (für Köche war heißes Wasser noch nie ein Mangelprodukt^^). Ich hab bereits auf den Artikel Entlassungskandidat hingewiesen. Der ist doch eigentlich für genaus solche Berichte und Erinnerungen gedacht, und daran arbeiten sicher mehr Leute mit Fachverstand hinsichtlich Militär und NVA als hier, wo es eigentlich eher um das Küchengerät gehen sollte. 00:10, 5. Dez. 2011 (CET) | C72: Nicht feststellbar | D72: Nicht feststellbar | E72: =IF(C72="NICHT-ANALYSIERT", "NA", IF(C72=D72, 1, 0)) -> 1
A73: 72 | B73: Um jetzt hier sachlich miteinander umzugehen von mir der Hinweis, im ganzen Artikel gibt es nur einen Satz zum Thema der ganze Schmu mit dem Kaffeekochen .... nämlich Für Soldaten der Nationalen Volksarmee und der Grenztruppen gab es für gewöhnlich nur nach Dienstschluss und nur in den Kompanieclubs die Möglichkeit Kaffee und andere Heißgetränke zu sich zu nehmen. Der Rest ist eben eine Beschreibung des Aufbaus und der Funktion des Gerätes und die Hintergründe. -- 20:11, 6. Dez. 2011 (CET) | C73: Nicht feststellbar | D73: Nicht feststellbar | E73: =IF(C73="NICHT-ANALYSIERT", "NA", IF(C73=D73, 1, 0)) -> 1
A74: 73 | B74: Oh, jetzt sind die Grenztruppen ja drin! Aber so (s.o.) stimmt das nicht: da hatte man durchaus die Möglichkeit *im Dienst* Kaffee und andere Heißgetränke zu sich zu nehmen. Thermosflaschen im Grenzdienst waren legal. Meist zwar mit Tee, aber Kaffee war organisierbar. Auch erlebt: Boiler (etwa so einer) in der Wachstube im Objektschutz so heiß wie möglich stellen (und das ging zwar nicht kochend, aber *sehr* heiß!) + *löslicher Kaffee*. War in den 80ern dank Delikat schließlich kein Weltwunder mehr. Also Zeitschiene beachten". -- 23:04, 6. Dez. 2011 (CET) " | C74: Nicht feststellbar | D74: Nicht feststellbar | E74: =IF(C74="NICHT-ANALYSIERT", "NA", IF(C74=D74, 1, 0)) -> 1
A75: 74 | B75: Um Oliver mal beizupflichten: im derzeitigen Stand steht im Artikel alles Wesentliche drin. Um nur mal ein Beispiel zu bringen: Soldaten durften nur nach Dienstschluss oder in Kompanieclubs Kaffee trinken, mancherorts aber auch anderswo. Dann kann man den Satz zu weglassen. Dass die Soldaten Kaffee mit einem selbstgebauten Tauchsieder kochten, wird ja auch so vermittelt. Der gestrichene Satz enthielt keine wesentliche Information. Gruß, -- 08:57, 12. Dez. 2011 (CET) | C75: Nicht feststellbar | D75: Nicht feststellbar | E75: =IF(C75="NICHT-ANALYSIERT", "NA", IF(C75=D75, 1, 0)) -> 1
A76: 75 | B76: Ich hätte wohl noch dazuschreiben sollen: Eine Kritik vor dem 11. September 2001"... Wie der Spiegel den Schwenk macht, das Buch in den 90er Jahren "eine eingehend dokumentierte Abrechnung mit den Machenschaften westlicher Dienste" zu nennen, um dann auf "Schmöker-Stoff auf James-Bond-Niveau" zu kommen, bleibt wohl sein Geheimnis. Aber da galt es halt, ihn möglichst effizient zu diskreditieren. Dass man verdeckte Operationen von Geheimdiensten, die gleich dutzendfach im Detail mit allen möglichen kriminellen Aspekten erwiesen und von Investigativjournalisten (zB Seymour Hersh) und (in den USA vor allem) Historikern (etwa Alfred McCoy) durchgekaut sind (siehe etwa Abschnitt "Bekannte Operation" bei CIA), pauschal als "James-Bond-Stoff" bezeichnet, wirft ein ziemlich deutliches Licht auf die Kompetenz bzw Intention des Schreibers, dem ich mal POVig abspreche, das Buch gelesen zu haben. Ein Thema des Buches ist zB die Verstrickung der CIA in den Drogenhandel, die längst kalter Kaffee ist und (natürlich fein auf irgendwelchen hinteren Seiten eines 1000seitigen Untersuchungsberichts versteckt) von der CIA selbst bestätigt wurde (siehe auch CIA#Drogenhandel_und_Geldw.C3.A4sche) Die Links zu den CIA-Untersuchungsberichten in Dark Alliance sind übrigens mittlerweile tot, ich werd da mal auf die Suche gehen.. Aber ich hab ja oben versprochen, mich dran zu halten - Spiegel bleibt Spiegel, obwohl er sich in dieser Richtung wirklich nicht mit Ruhm bekleckert. Also bezeichnet Bülow doch meinetwegen pauschal als Verschwörungstheoretiker. Mir solls recht sein. 20:33, 15. Jan. 2013 (CET) " | C76: Maskulinum oder Neutrum | D76: Maskulinum oder Neutrum | E76: =IF(C76="NICHT-ANALYSIERT", "NA", IF(C76=D76, 1, 0)) -> 1 | F76: Adjektivflexion, er
A77: 76 | B77: So - wenn ich den [http://opticalmineralogy.com/the-oxides-and-hydroxides-mineral-class/anatase| optische Mikroskopie-Anatas] (SEHR LESENSWERT!) ohne Kaffee richtig lese, erscheint die Interferenzfigur im Polarisationsmikroskop durch die Überlagerung der Absorption teilweise annormal biaxial. Zitat: It is usually found with numerous isochromes that are often masked by the mineral color. Some dark colored varieties of Anatase may exhibit anomalously biaxial negative figure." Somit sind die Interferenzfiguren biaxial, aber nicht unbedingt die Brechungsindices. -- 10:22, 13. Apr. 2012 (CEST) " | C77: Nicht feststellbar | D77: Nicht feststellbar | E77: =IF(C77="NICHT-ANALYSIERT", "NA", IF(C77=D77, 1, 0)) -> 1
A78: 77 | B78: S. 243: Auf der Autobahn war in jener Zeit ein sehr reger Verkehr von Militärfahrzeugen. Frauen, Männer und viele Kinder priesen an den Fahrbahnen schwarzgebrannten Rüben- oder Zwetschgenschnaps und im Herbst Früchte zum Tausch an. Obwohl den Truppen eine Fraternisierung streng verboten war, gingen zahlreiche Soldaten, vielfach Neger, auf die Händel ein. Leichtsinnige Mädchen verkauften Liebe gegen Zigaretten, Schokolade, Konserven, Kaffee etc. Was daran erfunden oder nicht den Tatsachen entsprechende sein könnte, ist mir (noch) unklar. Möglich, dass die Kausalität Truppentransporte auf der Autobahn -&amp;gt; Schwarzhandel und Prostitution" nicht so ausgeprägt ist wie durch den Satz angedeutet. Die schweren Raubüberfälle führt Gast auch nicht darauf, sondern auf von Amerikaner befreite Kriegsgefangene und Fremdarbeiter, vornehmlich Russen, Polen und Jugoslawen zurück. Von ihren Lagern (z.B. Oberkassel) aus unternahmen sie Raubzüge in die Umgebung, drangen nachts mit Schußwaffen in Häuser ein, erschossen die Bewohner und raubten, was irgendwie wertvoll schien. Dann nennt Gast mehrere Beispiele von Überfällen bei konkreten Personen. Inwieweit dies alles als Quelle für die Truppentransporte nicht ausreichen soll und weitere Quellen notwendig sind (für diese Forderung muss es ja eine Rechtfertigung geben), möchte ich lieber der Beurteilung anderer überlassen. Es war vermutlich Benutzer:SuCapitanidad, der diese Aussagen in den Artikel aufnahm.-- 10:01, 29. Aug. 2011 (CEST) " | C78: Nicht feststellbar | D78: Nicht feststellbar | E78: =IF(C78="NICHT-ANALYSIERT", "NA", IF(C78=D78, 1, 0)) -> 1
A79: 78 | B79: Leider konnten noch immer keine Belege für den Abschnitt Geschichte" (Zeittafel, Altreier Kaffee, Ortsnamen) gefunden werden. Habe nur für einen Absatz einen Beleg finden können. Evtl. stammen die Angaben aus dem Altreier Dorfbuch. Es stellt sich nun die Frage, den Abschnitt zu löschen. Ähnliches gilt für die Wappenbeschreibung. Abhilfe könnten die Quellen Egon Kühebacher, Die Ortsnamen Südtirols und ihre Geschichte, vol. 1, Bolzano, Athesia, 1995 und Cfr. Franz Huter, Archivberichte aus Altrei und Truden, in «Veröffentlichungen des Museums Ferdinandeum», 8 (Festschrift zu Ehren Oswald Redlichs), Innsbruck, Wagner, 1928 schaffen. -- 11:53, 10. Feb. 2013 (CET)timestamp " | C79: Nicht feststellbar | D79: Nicht feststellbar | E79: =IF(C79="NICHT-ANALYSIERT", "NA", IF(C79=D79, 1, 0)) -> 1 | F79: Altrier ist ein Ort (Altréier auf Luxemburgisch)
A80: 79 | B80: Masse ist nicht an Materie gebunden, bzw. man darf beide Begriffe nicht miteinander vermengen. Die Äquivalenzbeziehung besagt, dass man Energie an sich, also unabhängig ihrer Erscheinungsform, eine Masse zuordnen muss. Folglich besitzt eine heiße Tasse Kaffee eine grössere Masse als eine kalte Tasse aus identisch vielen Atomen, weil die höhere kinetische Energie der Atome der heißen Tasse zur Gesamtmasse beiträgt. Diese höhere Masse macht sich sowohl in einem erhöhten Impuls als auch in einem erhöhten Gewicht bemerkbar. Salopp gesprochen: heiße Tassen wiegen mehr als kalte. | C80: Nicht feststellbar | D80: Nicht feststellbar | E80: =IF(C80="NICHT-ANALYSIERT", "NA", IF(C80=D80, 1, 0)) -> 1
A81: 80 | B81: Historiker und die Stadtverwaltung haben sich auf dieses Datum als Gründungszeit geeinigt. ;-) Wie muss ich mir das vorstellen? Da lädt die Stadtverwaltung drei Historiker zum Kaffee und Kucken ein und die knobeln dann die Gründungszeit aus? ;-). Am besten ganz rauslassen. Oder soll damit zum Ausdruck gebracht werden, dass man Jubiläen wie zum Beispiel die 800-Jahr-Feier 1973 etc. gern von dem Datum aus berechnet? Dann vielleicht so: Das Datum wird allgemein auch für den Ursprung der späteren Stadt angenommen und Jubiläen darauf bezogen. Allgemein heißt dann bei Stadtverwaltung, Tourismuseinrichtingen, Heimatforschung etc. Historiker_innen dürften da aber wohl anderer Meinung sein, da ja eine Siedlung im Gebiet der eigentlichen Stadt Aue noch nicht bestanden haben muss, als das Klösterlein Zelle gegründet wurde. | C81: Maskulinum oder Neutrum | D81: Maskulinum oder Neutrum | E81: =IF(C81="NICHT-ANALYSIERT", "NA", IF(C81=D81, 1, 0)) -> 1 | F81: Präposition mit Artikel -> Zum
A82: 81 | B82: womit ein Autor von 4 Sachbüchern seinen Lebensunterhalt verdient und verdient hat, ist so irrelevant wie die Frage, ob er gern Kaffee oder lieber Tee trinkt. Ich kann es nur noch einmal gebetsmühlenartig wiederholen: wir veröffentlichen ausschließlich publiziertes Wissen. Und selbst in Artikeln berühmter Persönlichkeiten, über die Biografien geschrieben wurden, wählen wir aus, was wir veröffentlichen und was lexikalisch relevant ist.-- 17:09, 18. Sep. 2013 (CEST) | C82: Nicht feststellbar | D82: Nicht feststellbar | E82: =IF(C82="NICHT-ANALYSIERT", "NA", IF(C82=D82, 1, 0)) -> 1
A83: 82 | B83: Sakra, wie lange und wie oft willst du denn diesen kalten Kaffee wieder aufwärmen? Die Diskussion wurde längst dahin verlagert, wo sie hingehört: in die Diskussion zur Formtavorlage von biografischen Artikeln. Hier arbeiten wir nach den gültigen Konventionen und wie es Usus ist in WIKIPEDIA, solange kein Konsens für eine grundsätzliche Änderung erzielt wird.-- 20:53, 19. Sep. 2013 (CEST) | C83: Maskulinum oder Neutrum | D83: Maskulinum oder Neutrum | E83: =IF(C83="NICHT-ANALYSIERT", "NA", IF(C83=D83, 1, 0)) -> 1 | F83: Demonstrativpronomen -> diesen
A84: 83 | B84: Vor dem nächsten Humorversuch bitte noch nen Kaffee trinken. ;) Natürlich sind auch Teile des Programms der CDU inhaltlich rechtspopulistisch, Lucke hat Stoiber da ja sehr schön vorgeführt. Daran ändert auch die Tatsache nichts, dass die AfD (gemeinsame) migrantenfeindliche Inhalte polemisch zugespitzt im Wahlkampf plakatiert hat, was die CDU klugerweise lieber unterließ. Wer dennoch bei der CDU dazu was in den Artikel reinschreiben will und entsprechde Belege findet, ist dazu wie immer herzlich eingeladen. Grüße, -- 12:56, 22. Okt. 2013 (CEST) | C84: Maskulinum oder Neutrum | D84: Maskulinum oder Neutrum | E84: =IF(C84="NICHT-ANALYSIERT", "NA", IF(C84=D84, 1, 0)) -> 1 | F84: nen -> indefiniter Artikel
A85: 84 | B85: Ich habe Anfang 2009 unter dem Einfluss von Stress - über Monate anhaltender Lärm - Bluthochdruck bekommen. 24h-Messung 150/90 im Schnitt. Die üblichen Maßnahmen wie Joggen, Kaffee absetzen reichten nicht mehr aus. 1,5 Stunden danach war der Blutdruck wieder von 125/80 auf 150/87 angestiegen. | C85: Nicht feststellbar | D85: Nicht feststellbar | E85: =IF(C85="NICHT-ANALYSIERT", "NA", IF(C85=D85, 1, 0)) -> 1
A86: 85 | B86: Go for it. Ich hänge sicher nicht an dem Satz. Sie nennt diese Stereotype Tropes" kann imho dann auch gleich weg. Sie nennt dieses koffeinhaltige Getränk Kaffee würden wir auch nicht schreiben. -- 19:24, 6. Jun. 2015 (CEST) " | C86: Nicht feststellbar | D86: Nicht feststellbar | E86: =IF(C86="NICHT-ANALYSIERT", "NA", IF(C86=D86, 1, 0)) -> 1
A87: 86 | B87: Also Ulrich: Unabhängig von unseren fachlichen Differenzen hier trinke ich mit dir zusammen gerne einmal einen Kaffee ;-) - falls man sich eben mal wieder treffen sollte... Dann kann man ja mal wieder über Radwanderkartografie usw. quatschen. Damit Grüße nach Bremen. -- 03:30, 13. Dez. 2015 (CET) | C87: Maskulinum oder Neutrum | D87: Maskulinum oder Neutrum | E87: =IF(C87="NICHT-ANALYSIERT", "NA", IF(C87=D87, 1, 0)) -> 1 | F87: den -> definiter Artikel
A88: 87 | B88: Na Ulrich, alles wieder zurück gesetzt... Alles andere hätte mich auch gewundert... Jetzt schmollst du auch noch und ich bin für dich wohl eine Art Persona non grata"? ;-). Es sind und bleiben in dem Satz so aber falsche Tatsachen. Von meiner Seite ist nun echt alles zu möglichen Namensalternativen gesagt. Wie schon gesagt: "holprig übersetzt" -&amp;gt; siehe mobilogisch... Diese WP-Geschichte hier eignet sich mittlerweile sehr gut als nettes "Small-Talk-Thema" (wie soll das Kind denn im Deutschen heißen?) wenn ich evtl. mal wieder ein Fachseminar der Fahrradakademie besuchen sollte. Dann zücken die Leute schnell mal ihr Smartphone und können hier ja alles öffentlich nachlesen. Sonst bleibt das Angebot mit dem Kaffee aber gerne für die unbestimmte Zukunft bestehen. ;-)-- 01:15, 19. Dez. 2015 (CET) " | C88: Maskulinum oder Neutrum | D88: Maskulinum oder Neutrum | E88: =IF(C88="NICHT-ANALYSIERT", "NA", IF(C88=D88, 1, 0)) -> 1 | F88: dem -> definiter Artikel
A89: 88 | B89: @ Feliz: Eben wohl nicht, wenn man den Artikel Amok und aufgeführte Weblinks in beiden Artikeln vergleicht, Amoktaten haben eine Entwicklung (auch wenn die Taten für den Außenstehenden spontan erscheinen). Ansonsten stimme ich Zinnmanns Kommentar zu (Abwarten und Tee bzw Kaffee trinken) ;-)---- 13:53, 26. Sep. 2008 (CEST) | C89: Nicht feststellbar | D89: Nicht feststellbar | E89: =IF(C89="NICHT-ANALYSIERT", "NA", IF(C89=D89, 1, 0)) -> 1
A90: 89 | B90: Wie klar ist denn positioniert, wenn Sie hochoffiziell mit erstem Wohnsitz wieder in Polen wohnt? Kann ich nicht sehen. Eine Aussage vor der Presse ist soviel Wert wie kalter Kaffee. Aber mit Steffi Graf wird ja hier ähnlich verfahren: Sie lebt seit J (nicht signierter Beitrag von 13:27, 7. Feb. 2016 (CET)timestamp | C90: Maskulinum oder Neutrum | D90: Maskulinum oder Neutrum | E90: =IF(C90="NICHT-ANALYSIERT", "NA", IF(C90=D90, 1, 0)) -> 1 | F90: Adjektivflexion, er
A91: 90 | B91: Hat also keine überregionale Bedeutung, ja, und Strache war nur zum Kaffee in Düsseldorf? Der Rechtsextremismusforscher Volker Weiß schreibt: &#x201e;Dem Mitte Februar ausgehandelten Kooperationsbeschluss der AfD und der österreichischen FPÖ war eine gemeinsame Veranstaltung in Düsseldorf vorausgegangen. Unter dem Motto »Europäische Visionen &#x2013; Visionen für Europa« traten dort Frauke Petry und der nordrhein-westfälische AfD-Vorsitzende Marcus Pretzell mit den FPÖ-Spitzenfunktionären Hans-Christian Strache und Harald Vilimsky zusammen. Zukünftig wolle man den Austausch intensivieren, hieß es.&#x201c;-- 19:38, 21. Mär. 2016 (CET)timestamp | C91: Maskulinum oder Neutrum | D91: Maskulinum oder Neutrum | E91: =IF(C91="NICHT-ANALYSIERT", "NA", IF(C91=D91, 1, 0)) -> 1 | F91: zum -> Präposition mit einem bestimmten Artikel
A92: 91 | B92: Erstens: Die Bibel ist in keinem Teil älter als 1500 Jahre. Zweitens: Ihre pseudogeschichtlichen Inhalte weichen von archäologisch gesicherten Fakten derart ab daß man sie als historische Überlieferung nicht verwenden kann. Beispiel: Juden in Ägypten - hats nie gegeben. Genausowenig wie eine Vertreibung durch einen Pharao. Drittens: Es besteht anz einfach nicht die Notwendigkeit die Bibel derart zu interpretieren und analysieren wie es im bisherigen Artikel der Fall ist. Änliches ist für die Literatur des Fliegenden Spaghetti Monsters jedenfalls nicht der Fall. Viertens: welche Wut? Ich habe lediglich eine Sichtweise dargelegt - ich bin mir schon klar darüber daß sie z.T.sehr spitz ist - aber letztlich meine ich durchaus berechtigt. Die Bibel und Einfluß auf die Menschen? Hast Du die Bibel mal gelesen? Es gibt kaum ein Buch das weniger Bezug zur realen Welt hat als dieses. Kraft, Inspiration und Mut kann man auch aus anderen hierfür besser geeigneten Büchern schöpfen. Man kann sie auch dafür benutzen damit der Tisch nicht mehr wackelt. Wozu jeder ganz individuell ein Buch benutzt, und wenn es als Brennmaterial ist, ist doch völlig egal - das ist so logisch daß es speziell im Artikel über ein bestimmtes Buch nix verloren hat. Ich persönlich schöpfe Kraft, Mut und wasweißich aus einer schönen Mittagpause und ner Tasse Kaffee. Gut, letztlich gebe ich eines zu: die Stimmen hier in der Diskussion die selbst andere vergleichbare Literatur sowie die Kritik an der Bibel verbannen wollten hat mich dazu bewegt mal einen Diskussionsbeitrag in die andere Richtung zu schreiben. Es war sehr interessant zu beobachten was so als Reaktion kommt ;) | C92: Nicht feststellbar | D92: Nicht feststellbar | E92: =IF(C92="NICHT-ANALYSIERT", "NA", IF(C92=D92, 1, 0)) -> 1
A93: 92 | B93: Diese Diskussion koennte weiter zu 'fruchtbaren' Gedankenansaetzen fuehren; weiss zwar nicht, mit wem ich hier 'Meinungen/Argumente' austausche, aber das ist auch unerheblich. Ich liebe dieses Land und leide unter seiner 'unprofessionellen' (man koennte das auch erheblich drastischer formulieren!) Fuehrung. Habe selbst die Entwicklung nach 91/92 im Osten Europas (e.g; Baltische Staaten!) mit begleiten duerfen; das ist zu dem, was sich seit 98/99 in BiH abgespiel hat', geradezu ein Maerchen. - Warum? - weil Esten, Letten und Littauer WOLLTEN! - Dieser Wille ist auch bei den BOSNIERN lebendig; in der Altstadt bei Kaffee und / oder Raki findest Du keine 'Nationalisten'! - Nur kurz zur Wechselkurs-Debatte: Wenn morgen BiH 'freigegeben' wird, ist das Land (nicht Staat oder Nation!) uebermorgen bankrott! Nur - diejenigen, die das zu verantworten haben, die haben laengst ihre Datscha an der kroatischen Kueste ... oder ... !? Ueber nunmehr mehr als zehn Jahre quaelt sich der sogenannte internationale 'Integrationsprozess' Bosniens ... voran? Aber wie soll das auch gehen, wenn politische 'Eliten' im Land keinen Deut an interner Integrationsbereitschaft zeigen. (nicht signierter Beitrag von 15:35, 13. Jul 2010 (CEST) | C93: Nicht feststellbar | D93: Nicht feststellbar | E93: =IF(C93="NICHT-ANALYSIERT", "NA", IF(C93=D93, 1, 0)) -> 1
A94: 93 | B94: Deine Version stellt eine Nähe zum rechtsextremen Spektrum als Tatsache dar (&#x201e;... aufgrund seiner Nähe ...&#x201c;) und behauptet, dass seine Aufgabe umstritten sei. Das ist sie nicht, denn sie ist im Bundesverfassungsschutzgesetz, § 3 festgelegt. Umstritten kann höchstens sein, ob das BfV dieser Aufgabe gerecht wird. Nun könntest Du schreiben: &#x201e;Es ist umstritten, ob das BfV seiner Aufgabe gerecht wird.&#x201c; Das wäre kalter Kaffee: Das trifft auf fast jede politische Organisation zu. In einen enzyklopädischen Artikel gehören Tatsachen mit Informationswert, keine Allgemeinplätze. Diese Tatsachen, die konkreten Kritikpunkte, stehen bereits unten im Artikel. | C94: Maskulinum oder Neutrum | D94: Maskulinum oder Neutrum | E94: =IF(C94="NICHT-ANALYSIERT", "NA", IF(C94=D94, 1, 0)) -> 1 | F94: Adjektivflexion, er
A95: 94 | B95: Als Symbol für die Abwendung von England verzichteten die US-Amerikaner fortan auf den Teekonsum und entdeckten statt dessen ihre Liebe zum Kaffee. Bis heute ist Kaffee das Nationalgetränk während erst in den letzten Jahren der Tee als Modegetränk und Gesundheitselexier wiederentdeckt wurde. | C95: Maskulinum oder Neutrum | D95: Maskulinum oder Neutrum | E95: =IF(C95="NICHT-ANALYSIERT", "NA", IF(C95=D95, 1, 0)) -> 1 | F95: zum -> Präposition mit einem bestimmten Artikel
A96: 95 | B96: Ja, hab ich :) Denn ehrlicherweise hätte ich mich ohne das beruhigende Aroma von Kaffee über den ersten Abschnitt des Artikels wirklich sehr aufgeregt. Man muss nicht einflechten, dass Ohnesorg gut mit Kindern umgehen konnte, nur um zu zeigen, dass er kein schlechter Mensch war. Dies hat in einer Biographie Platz (mit vielen anderen Anekdoten). Es steht ja auch nicht bei Maria Theresia, dass selbige gut mit Kindern konnte. Wovon freilich auszugehen ist, da sie 16 an der Zahl hatte. 09:55, 23. Aug. 2008 (CEST) | C96: Nicht feststellbar | D96: Nicht feststellbar | E96: =IF(C96="NICHT-ANALYSIERT", "NA", IF(C96=D96, 1, 0)) -> 1
A97: 96 | B97: Das Wappen stammt aus den von O. Hupp gesammelten Ortswappen des Königreichs Preussen, Heft 5 (Provinz Pommern), die als Sammelbilder der Fa. Kaffee Hag, Bremen 1914 herausgegeben wurden (). Das aktuelle wird aber demnächst eingestellt. 18:55, 7. Mär 2006 (CET) | C97: Nicht feststellbar | D97: Nicht feststellbar | E97: =IF(C97="NICHT-ANALYSIERT", "NA", IF(C97=D97, 1, 0)) -> 1
A98: 97 | B98: Wenn Du einen Admin einschalten möchtest, gerne! Ich kenne zwei, einer kommt mal auf ein Bier oder Kaffee vorbei, wenn der in der Nähe ist. Diesbezüglich kann ich nur positive Meldungen verzeichnen, habe aber darauf bestanden, daß dies unter uns geregelt wird!!!!! | C98: Nicht feststellbar | D98: Nicht feststellbar | E98: =IF(C98="NICHT-ANALYSIERT", "NA", IF(C98=D98, 1, 0)) -> 1
A99: 98 | B99: Ich stell mich bei der CeBIT mal an den Bahnsteig und zähle, wenn ihr mir einen Kaffee vorbeibringt ;-). Die Zahlen verändern sich jährlich, sind auch bei CeBIT und Industriemesse unterschiedlich. Außerdem gibt es auch andere Messen mit verstärktem Verkehr. Wer weiß wirklich, wieviel Züge da halten, auch die S8 und S4 Verstärkung stehen nicht im Kursbuch. WP ist keine Auskunftei, sondern eine Enzyklopädie, das heißt eine geschichtliche Sehweise ist schon von Nöten.-- 16:53, 5. Feb. 2010 (CET)timestamp | C99: Maskulinum oder Neutrum | D99: Maskulinum oder Neutrum | E99: =IF(C99="NICHT-ANALYSIERT", "NA", IF(C99=D99, 1, 0)) -> 1 | F99: Indefiniter Artikel -> en
A100: 99 | B100: Natürliche Karzinogene in Kaffee | C100: Nicht feststellbar | D100: Nicht feststellbar | E100: =IF(C100="NICHT-ANALYSIERT", "NA", IF(C100=D100, 1, 0)) -> 1
...

Sheet Statistik
B2: Ergebnis | C2: Genuszuweisung (manuell) | E2: Genuszuweisung (Algorithmus) | G2: Differenz
C3: n | D3: % | E3: n | F3: % | G3: n | H3: %
B4: Nicht feststellbar | C4: =COUNTIF('Manuelle Überprüfung von 150'!C2:C943, B4) -> 82 | D4: =C4/C$7 -> 0.54666667 | E4: =COUNTIF('Manuelle Überprüfung von 150'!D2:D943, B4) -> 83 | F4: =E4/E$7 -> 0.55333333 | G4: =C4-E4 -> -1 | H4: =F4-D4 -> 0.0066666667
B5: Maskulinum oder Neutrum | C5: =COUNTIF('Manuelle Überprüfung von 150'!C2:C944, B5) -> 68 | D5: =C5/C$7 -> 0.45333333 | E5: =COUNTIF('Manuelle Überprüfung von 150'!D2:D944, B5) -> 65 | F5: =E5/E$7 -> 0.43333333 | G5: =C5-E5 -> 3 | H5: =F5-D5 -> -0.02
B6: Femininum | C6: =COUNTIF('Manuelle Überprüfung von 150'!C2:C945, B6) -> 0 | D6: =C6/C$7 -> 0 | E6: =COUNTIF('Manuelle Überprüfung von 150'!D2:D945, B6) -> 2 | F6: =E6/E$7 -> 0.013333333 | G6: =C6-E6 -> -2 | H6: =F6-D6 -> 0.013333333
B7: Summe | C7: =SUM(C4:C6) -> 150 | D7: =SUM(D4:D6) -> 1 | E7: =SUM(E4:E6) -> 150 | F7: =SUM(F4:F6) -> 1 | G7: =SUM(G4:G6) -> 0 | H7: =SUM(H4:H6) -> 8.1532003e-17
C9: n | D9: %
B10: Absolute Differenz | C10: =ABS(G4)+ABS(G5)+ABS(G6) -> 6 | D10: =C10/C7 -> 0.04
B12: Korrektheit | C12: n | D12: %
B13: Inkorrekte Ergebnisse | C13: =COUNTIF('Manuelle Überprüfung von 150'!E1:E944, 0) -> 7 | D13: =C13/(C13+C14) -> 0.046666667
B14: Korrekte Ergebnisse | C14: =COUNTIF('Manuelle Überprüfung von 150'!E1:E944, 1) -> 143 | D14: =C14/(C13+C14) -> 0.95333333
